Workbook

Sheet Instructions
B1: Bonus Depreciation and Section 179 Planner (OBBBA 2026)
B3: What changed under OBBBA
B4: The One Big Beautiful Bill Act (OBBBA), signed July 4, 2025, permanently restored 100% bonus depreciation for qualified property acquired and placed in service after January 19, 2025. The phase-down that had bonus at 40% for 2025 no longer applies to qualifying property.
B5: OBBBA also raised the Section 179 expensing limit to $2,500,000 with a $4,000,000 phase-out threshold for tax years beginning in 2025. Both amounts are inflation-indexed: for 2026 they are $2,560,000 and $4,090,000. The Section 179 deduction phases out dollar for dollar once total qualifying property placed in service exceeds the threshold.
B6: State conformity varies. California and New York notably decouple from federal bonus depreciation, so your state depreciation schedule may differ from the federal numbers this planner computes.
B8: How to use this planner
B9: 1. On the Settings sheet, pick your tax year (2025 or 2026) in the yellow cell. The Section 179 limit and phase-out threshold update automatically.
B10: 2. On the Asset Planner sheet, enter each planned asset purchase in the yellow cells: description, date placed in service, cost, recovery period (dropdown: 3, 5, 7, or 15 years), and business use %.
B11: 3. Pick an election for each asset from the dropdown: Bonus 100%, Section 179, or MACRS only. Eligible Basis and First-Year Deduction compute automatically. MACRS only uses the half-year convention first-year rate for the asset's recovery period.
B12: 4. Check the Section 179 limit check block below the totals row. It totals your Section 179 elections, applies the year's limit and the phase-out reduction, and shows remaining capacity. If you are over the limit, the warning cell tells you to shift the excess to Bonus.
B14: Worked example (prefilled)
B15: The planner ships with 6 sample assets. For example, the $850,000 CNC machine (7-year property, 100% business use) elected under Section 179 produces an $850,000 first-year deduction, while the $45,000 office furniture under MACRS only deducts 14.29% ($6,431) in year one. Replace the samples with your own purchases.
... B19: This is planning math, not tax advice. Confirm elections with your CPA and check your state's conformity rules before filing.

Sheet Settings
A1: Settings
A3: Tax year (pick 2025 or 2026) | B3: 2026 | C3: Input cell. Drives the Section 179 limit and phase-out threshold below.
A5: Section 179 expensing limit | B5: =IF(B3=2025,2500000,2560000) | C5: $2,500,000 for 2025; inflation-indexed to $2,560,000 for 2026 (OBBBA).
A6: Section 179 phase-out threshold | B6: =IF(B3=2025,4000000,4090000) | C6: $4,000,000 for 2025; $4,090,000 for 2026. Limit shrinks dollar for dollar above this.
A8: MACRS first-year rates (half-year convention, 200% DB)
A9: Recovery period (years) | B9: First-year rate
A10: 3 | B10: 0.3333
A11: 5 | B11: 0.2
A12: 7 | B12: 0.1429
A13: 15 | B13: 0.05
A15: Used by the Asset Planner via VLOOKUP for MACRS only elections.

Sheet Asset Planner
A1: Asset Description | B1: Date Placed in Service | C1: Cost | D1: Recovery Period (Years) | E1: Business Use % | F1: Election | G1: Eligible Basis | H1: First-Year Deduction | I1: Notes / Flags
A2: CNC machining center | B2: 46096 | C2: 850000 | D2: 7 | E2: 1 | F2: Section 179 | G2: =C2*E2 | H2: =IF(F2="Bonus 100%",G2,IF(F2="Section 179",G2,IF(F2="MACRS only",G2*VLOOKUP(D2,Settings!$A$10:$B$13,2,FALSE),0))) | I2: =IF(AND(F2="Bonus 100%",B2<=DATE(2025,1,19)),"Check: 100% bonus requires acquired and placed in service after Jan 19, 2025",IF(F2="MACRS only","Half-year convention year 1; remaining basis depreciates over the recovery period",IF(F2="Section 179","Counts toward the Section 179 limit check below","Fully deducted in year 1")))
A3: Delivery trucks (3 units) | B3: 46063 | C3: 210000 | D3: 5 | E3: 1 | F3: Section 179 | G3: =C3*E3 | H3: =IF(F3="Bonus 100%",G3,IF(F3="Section 179",G3,IF(F3="MACRS only",G3*VLOOKUP(D3,Settings!$A$10:$B$13,2,FALSE),0))) | I3: =IF(AND(F3="Bonus 100%",B3<=DATE(2025,1,19)),"Check: 100% bonus requires acquired and placed in service after Jan 19, 2025",IF(F3="MACRS only","Half-year convention year 1; remaining basis depreciates over the recovery period",IF(F3="Section 179","Counts toward the Section 179 limit check below","Fully deducted in year 1")))
A4: Server and network hardware | B4: 46143 | C4: 120000 | D4: 5 | E4: 1 | F4: Bonus 100% | G4: =C4*E4 | H4: =IF(F4="Bonus 100%",G4,IF(F4="Section 179",G4,IF(F4="MACRS only",G4*VLOOKUP(D4,Settings!$A$10:$B$13,2,FALSE),0))) | I4: =IF(AND(F4="Bonus 100%",B4<=DATE(2025,1,19)),"Check: 100% bonus requires acquired and placed in service after Jan 19, 2025",IF(F4="MACRS only","Half-year convention year 1; remaining basis depreciates over the recovery period",IF(F4="Section 179","Counts toward the Section 179 limit check below","Fully deducted in year 1")))
A5: Office furniture and fixtures | B5: 46132 | C5: 45000 | D5: 7 | E5: 1 | F5: MACRS only | G5: =C5*E5 | H5: =IF(F5="Bonus 100%",G5,IF(F5="Section 179",G5,IF(F5="MACRS only",G5*VLOOKUP(D5,Settings!$A$10:$B$13,2,FALSE),0))) | I5: =IF(AND(F5="Bonus 100%",B5<=DATE(2025,1,19)),"Check: 100% bonus requires acquired and placed in service after Jan 19, 2025",IF(F5="MACRS only","Half-year convention year 1; remaining basis depreciates over the recovery period",IF(F5="Section 179","Counts toward the Section 179 limit check below","Fully deducted in year 1")))
A6: Parking lot land improvements | B6: 46203 | C6: 95000 | D6: 15 | E6: 1 | F6: Bonus 100% | G6: =C6*E6 | H6: =IF(F6="Bonus 100%",G6,IF(F6="Section 179",G6,IF(F6="MACRS only",G6*VLOOKUP(D6,Settings!$A$10:$B$13,2,FALSE),0))) | I6: =IF(AND(F6="Bonus 100%",B6<=DATE(2025,1,19)),"Check: 100% bonus requires acquired and placed in service after Jan 19, 2025",IF(F6="MACRS only","Half-year convention year 1; remaining basis depreciates over the recovery period",IF(F6="Section 179","Counts toward the Section 179 limit check below","Fully deducted in year 1")))
A7: Company vehicle (mixed use) | B7: 46086 | C7: 65000 | D7: 5 | E7: 0.8 | F7: MACRS only | G7: =C7*E7 | H7: =IF(F7="Bonus 100%",G7,IF(F7="Section 179",G7,IF(F7="MACRS only",G7*VLOOKUP(D7,Settings!$A$10:$B$13,2,FALSE),0))) | I7: =IF(AND(F7="Bonus 100%",B7<=DATE(2025,1,19)),"Check: 100% bonus requires acquired and placed in service after Jan 19, 2025",IF(F7="MACRS only","Half-year convention year 1; remaining basis depreciates over the recovery period",IF(F7="Section 179","Counts toward the Section 179 limit check below","Fully deducted in year 1")))
A8: TOTALS | C8: =SUM(C2:C7) | G8: =SUM(G2:G7) | H8: =SUM(H2:H7)
A10: Section 179 limit check
A11: Total Section 179 elected | B11: =SUMIF(F2:F7,"Section 179",G2:G7) | C11: Sum of eligible basis for assets elected under Section 179
A12: Total qualifying property additions | B12: =C8 | C12: Total cost placed in service; drives the phase-out
A13: Section 179 limit (from Settings) | B13: =Settings!B5 | C13: Set by the tax year on the Settings sheet
A14: Phase-out reduction | B14: =MAX(0,B12-Settings!B6) | C14: Dollar for dollar reduction above the phase-out threshold
A15: Allowed Section 179 limit after phase-out | B15: =MAX(0,B13-B14) | C15: Limit minus phase-out reduction, floored at zero
A16: Remaining Section 179 capacity | B16: =B15-B11 | C16: Negative means you elected more than the allowed limit
A17: Status | B17: =IF(B11>B15,"OVER LIMIT: shift excess to Bonus","OK: within Section 179 limit")
