Workbook

Sheet Start Here
A1: Debt Covenant Compliance Calculator
A4: A controlled monthly workflow for agreement terms, calculations, headroom, downside cases, and reviewer sign-off.
A6: How to use this workbook
A7: 1. Read the signed credit agreement and enter the exact covenant definitions and thresholds in Agreement Terms.
A8: 2. Enter period-end balances and trailing-period measures in Financial Inputs. Keep source references with every amount.
A9: 3. Review Covenant Tests. Investigate any warning or failed result before preparing a compliance certificate.
A10: 4. Use Forecast Cases to test headroom under downside assumptions for EBITDA, debt, interest, and liquidity.
A11: 5. Complete the Summary sign-off only after the workbook ties to the general ledger and supporting schedules.
A14: Control notes
A15: Blue text | B15: Editable input
A16: Black text | B16: Formula or linked result
A17: Green | B17: Pass
A18: Amber | B18: Limited headroom or review required
A19: Red | B19: Failed covenant or missing support
A22: Important: Credit agreement definitions govern. This workbook is an operational aid, not legal, accounting, or lending advice. Have counsel and the lender confirm interpretations when terms are ambiguous.

Sheet Agreement Terms
A1: Agreement Terms and Covenant Definitions
A4: Enter the exact terms from the executed agreement and amendments. Do not substitute a generic formula.
A6: Field | B6: Input | C6: Unit | D6: Effective Date | E6: Agreement Reference | F6: Definition Note
A7: Borrower | B7: Northstar Components LLC | C7: Text | D7: 46023 | E7: Credit Agreement 6.11 | F7: Legal borrower and guarantor group
A8: Testing Period End | B8: 46203 | C8: Date | D8: 46023 | E8: Credit Agreement 7.02 | F8: Quarterly testing date
A9: Maximum Net Leverage | B9: 3.5 | C9: Ratio | D9: 46023 | E9: Credit Agreement 7.11(a) | F9: Net funded debt divided by adjusted EBITDA
A10: Minimum Interest Coverage | B10: 3 | C10: Ratio | D10: 46023 | E10: Credit Agreement 7.11(b) | F10: Adjusted EBITDA divided by cash interest
A11: Minimum Fixed Charge Coverage | B11: 1.25 | C11: Ratio | D11: 46023 | E11: Credit Agreement 7.11(c) | F11: Agreement-defined numerator divided by fixed charges
A12: Minimum Liquidity | B12: 500000 | C12: Currency | D12: 46023 | E12: Credit Agreement 7.11(d) | F12: Unrestricted cash plus eligible revolver availability
A13: Cash Netting Cap | B13: 1000000 | C13: Currency | D13: 46023 | E13: Definitions - Net Debt | F13: Maximum cash permitted to reduce funded debt
A14: Warning Band | B14: 0.15 | C14: Percentage | D14: 46023 | E14: Internal policy | F14: Flag when less than 15 percent of threshold remains
A15: EBITDA Add-backs Permitted | B15: Yes | C15: Yes or No | D15: 46023 | E15: Definitions - EBITDA | F15: Subject to agreement caps and evidence
A16: Currency | B16: USD | C16: Text | D16: 46023 | E16: Credit Agreement 1.01 | F16: Reporting currency

Sheet Financial Inputs
A1: Financial Inputs and Source References
A4: Use trailing twelve-month amounts unless the agreement specifies another period. Tie every input to a controlled source.
A6: Measure | B6: Amount | C6: Period | D6: Source Status | E6: Source Reference | F6: Review Note
A7: Funded debt | B7: 5400000 | C7: Period end | D7: Tied | E7: Debt rollforward 2026-Q2 | F7: Includes revolver and term debt
A8: Unrestricted cash | B8: 600000 | C8: Period end | D8: Tied | E8: Bank reconciliation 2026-06 | F8: Excludes restricted payroll cash
A9: Revolver availability | B9: 250000 | C9: Period end | D9: Tied | E9: Borrowing base 2026-06 | F9: Eligible unused availability
A10: Reported EBITDA | B10: 1400000 | C10: Trailing 12 months | D10: Tied | E10: Consolidated P&L 2026-Q2 | F10: Before permitted add-backs
A11: Permitted add-backs | B11: 200000 | C11: Trailing 12 months | D11: Reviewed | E11: Add-back schedule 2026-Q2 | F11: Integration and restructuring costs
A12: Cash interest expense | B12: 400000 | C12: Trailing 12 months | D12: Tied | E12: Interest rollforward 2026-Q2 | F12: Cash paid and accrued per agreement
A13: Scheduled principal | B13: 350000 | C13: Next 12 months | D13: Tied | E13: Debt schedule 2026-Q2 | F13: Required amortization
A14: Unfinanced capital expenditures | B14: 200000 | C14: Trailing 12 months | D14: Tied | E14: Fixed asset rollforward 2026-Q2 | F14: Excludes financed purchases
A15: Cash taxes | B15: 150000 | C15: Trailing 12 months | D15: Tied | E15: Tax payment schedule 2026-Q2 | F15: Cash taxes paid
A16: Restricted payments | B16: 50000 | C16: Trailing 12 months | D16: Reviewed | E16: Equity ledger 2026-Q2 | F16: Distributions included by agreement
A17: Intercompany eliminations | B17: 0 | C17: Trailing 12 months | D17: Tied | E17: Consolidation workpaper 2026-Q2 | F17: No net impact after elimination

Sheet Covenant Tests
A1: Covenant Tests and Headroom
A4: Formula-driven results. Warning means the covenant passes but remaining headroom is below the internal warning band.
A6: Covenant | B6: Calculation | C6: Actual | D6: Threshold | E6: Headroom | F6: Headroom % | G6: Status | H6: Review Note
A7: Net Leverage | B7: (Debt - permitted cash) / Adjusted EBITDA | C7: =('Financial Inputs'!B7-MIN('Financial Inputs'!B8,'Agreement Terms'!B12))/('Financial Inputs'!B10+'Financial Inputs'!B11) -> 3 | D7: ='Agreement Terms'!B9 -> 3.5 | E7: =D7-C7 -> 0.5 | F7: =E7/D7 -> 0.142857 | G7: =IF(C7>D7,"Fail",IF(F7<'Agreement Terms'!B13,"Warning","Pass")) -> Warning | H7: Review downside sensitivity before certificate
A8: Interest Coverage | B8: Adjusted EBITDA / Cash interest | C8: =('Financial Inputs'!B10+'Financial Inputs'!B11)/'Financial Inputs'!B12 -> 4 | D8: ='Agreement Terms'!B10 -> 3 | E8: =C8-D8 -> 1 | F8: =E8/D8 -> 0.333333 | G8: =IF(C8<D8,"Fail",IF(F8<'Agreement Terms'!B13,"Warning","Pass")) -> Pass
A9: Fixed Charge Coverage | B9: (EBITDA - capex - taxes - distributions) / fixed charges | C9: =(('Financial Inputs'!B10+'Financial Inputs'!B11)-'Financial Inputs'!B14-'Financial Inputs'!B15-'Financial Inputs'!B16)/('Financial Inputs'!B12+'Financial Inputs'!B13) -> 1.6 | D9: ='Agreement Terms'!B11 -> 1.25 | E9: =C9-D9 -> 0.35 | F9: =E9/D9 -> 0.28 | G9: =IF(C9<D9,"Fail",IF(F9<'Agreement Terms'!B13,"Warning","Pass")) -> Pass
A10: Minimum Liquidity | B10: Unrestricted cash + revolver availability | C10: ='Financial Inputs'!B8+'Financial Inputs'!B9 -> 850000 | D10: ='Agreement Terms'!B12 -> 500000 | E10: =C10-D10 -> 350000 | F10: =E10/D10 -> 0.7 | G10: =IF(C10<D10,"Fail",IF(F10<'Agreement Terms'!B13,"Warning","Pass")) -> Pass
A13: Supporting calculations
A14: Adjusted EBITDA | B14: ='Financial Inputs'!B10+'Financial Inputs'!B11 -> 1600000
A15: Cash permitted to net | B15: =MIN('Financial Inputs'!B8,'Agreement Terms'!B12) -> 600000
A16: Net debt | B16: ='Financial Inputs'!B7-B15 -> 4800000
A17: Fixed charge numerator | B17: =B14-'Financial Inputs'!B14-'Financial Inputs'!B15-'Financial Inputs'!B16 -> 1200000
A18: Fixed charge denominator | B18: ='Financial Inputs'!B12+'Financial Inputs'!B13 -> 750000

Sheet Forecast Cases
A1: Forward Covenant Headroom
A4: Edit blue assumption cells to test the next reporting period. These cases do not replace a full forecast.
A6: Scenario | B6: EBITDA Change | C6: Debt Change | D6: Interest Change | E6: Liquidity Change | F6: Net Leverage | G6: Interest Coverage | H6: Overall Status
A7: Base Case | B7: 0 | C7: 0 | D7: 0 | E7: 0 | F7: =(('Financial Inputs'!B7+C7)-MIN('Financial Inputs'!B8,'Agreement Terms'!B12))/(('Covenant Tests'!B14)*(1+B7)) -> 3 | G7: =(('Covenant Tests'!B14)*(1+B7))/('Financial Inputs'!B12*(1+D7)) -> 4 | H7: =IF(OR(F7>'Agreement Terms'!B9,G7<'Agreement Terms'!B10,('Covenant Tests'!C10+E7)<'Agreement Terms'!B12),"Fail",IF(OR(('Agreement Terms'!B9-F7)/'Agreement Terms'!B9<'Agreement Terms'!B13,(G7-'Agreement Terms'!B10)/'Agreement Terms'!B10<'Agreement Terms'!B13),"Warning","Pass")) -> Warning
A8: 10 Percent EBITDA Downside | B8: -0.1 | C8: 0 | D8: 0.05 | E8: -100000 | F8: =(('Financial Inputs'!B7+C8)-MIN('Financial Inputs'!B8,'Agreement Terms'!B12))/(('Covenant Tests'!B14)*(1+B8)) -> 3.333333 | G8: =(('Covenant Tests'!B14)*(1+B8))/('Financial Inputs'!B12*(1+D8)) -> 3.428571 | H8: =IF(OR(F8>'Agreement Terms'!B9,G8<'Agreement Terms'!B10,('Covenant Tests'!C10+E8)<'Agreement Terms'!B12),"Fail",IF(OR(('Agreement Terms'!B9-F8)/'Agreement Terms'!B9<'Agreement Terms'!B13,(G8-'Agreement Terms'!B10)/'Agreement Terms'!B10<'Agreement Terms'!B13),"Warning","Pass")) -> Warning
A9: 20 Percent EBITDA Downside | B9: -0.2 | C9: 250000 | D9: 0.1 | E9: -200000 | F9: =(('Financial Inputs'!B7+C9)-MIN('Financial Inputs'!B8,'Agreement Terms'!B12))/(('Covenant Tests'!B14)*(1+B9)) -> 3.945313 | G9: =(('Covenant Tests'!B14)*(1+B9))/('Financial Inputs'!B12*(1+D9)) -> 2.909091 | H9: =IF(OR(F9>'Agreement Terms'!B9,G9<'Agreement Terms'!B10,('Covenant Tests'!C10+E9)<'Agreement Terms'!B12),"Fail",IF(OR(('Agreement Terms'!B9-F9)/'Agreement Terms'!B9<'Agreement Terms'!B13,(G9-'Agreement Terms'!B10)/'Agreement Terms'!B10<'Agreement Terms'!B13),"Warning","Pass")) -> Fail
A10: Management Case | B10: 0.08 | C10: -300000 | D10: -0.05 | E10: 100000 | F10: =(('Financial Inputs'!B7+C10)-MIN('Financial Inputs'!B8,'Agreement Terms'!B12))/(('Covenant Tests'!B14)*(1+B10)) -> 2.604167 | G10: =(('Covenant Tests'!B14)*(1+B10))/('Financial Inputs'!B12*(1+D10)) -> 4.547368 | H10: =IF(OR(F10>'Agreement Terms'!B9,G10<'Agreement Terms'!B10,('Covenant Tests'!C10+E10)<'Agreement Terms'!B12),"Fail",IF(OR(('Agreement Terms'!B9-F10)/'Agreement Terms'!B9<'Agreement Terms'!B13,(G10-'Agreement Terms'!B10)/'Agreement Terms'!B10<'Agreement Terms'!B13),"Warning","Pass")) -> Pass

Sheet Summary
A1: Debt Covenant Compliance Summary
A3: Prepared from agreement-specific definitions and controlled financial inputs
A5: Borrower | B5: ='Agreement Terms'!B7 -> Northstar Components LLC | C5: Period End | D5: ='Agreement Terms'!B8 -> 46203 | E5: Prepared By | F5: Taylor Morgan | G5: Overall Status | H5: =IF(COUNTIF('Covenant Tests'!G7:G10,"Fail")>0,"Fail",IF(COUNTIF('Covenant Tests'!G7:G10,"Warning")>0,"Warning","Pass")) -> Warning
A7: Covenant results
A8: Covenant | B8: Actual | C8: Threshold | D8: Headroom | E8: Status | F8: Agreement Reference | G8: Evidence Status | H8: Reviewer Note
A9: Net Leverage | B9: ='Covenant Tests'!C7 -> 3 | C9: ='Covenant Tests'!D7 -> 3.5 | D9: ='Covenant Tests'!E7 -> 0.5 | E9: ='Covenant Tests'!G7 -> Warning | F9: 7.11(a) | G9: Complete | H9: Downside case required
A10: Interest Coverage | B10: ='Covenant Tests'!C8 -> 4 | C10: ='Covenant Tests'!D8 -> 3 | D10: ='Covenant Tests'!E8 -> 1 | E10: ='Covenant Tests'!G8 -> Pass | F10: 7.11(b) | G10: Complete
A11: Fixed Charge Coverage | B11: ='Covenant Tests'!C9 -> 1.6 | C11: ='Covenant Tests'!D9 -> 1.25 | D11: ='Covenant Tests'!E9 -> 0.35 | E11: ='Covenant Tests'!G9 -> Pass | F11: 7.11(c) | G11: Complete
A12: Minimum Liquidity | B12: ='Covenant Tests'!C10 -> 850000 | C12: ='Covenant Tests'!D10 -> 500000 | D12: ='Covenant Tests'!E10 -> 350000 | E12: ='Covenant Tests'!G10 -> Pass | F12: 7.11(d) | G12: Complete
A15: Forecast alert
A16: Downside case | B16: Projected leverage | C16: Projected coverage | D16: Projected liquidity | E16: Status | F16: Required action
A17: 20 Percent EBITDA Downside | B17: ='Forecast Cases'!F9 -> 3.945313 | C17: ='Forecast Cases'!G9 -> 2.909091 | D17: ='Covenant Tests'!C10+'Forecast Cases'!E9 -> 650000 | E17: ='Forecast Cases'!H9 -> Fail | F17: Escalate before certificate delivery
A20: Review and sign-off
A21: Prepared By | B21: Taylor Morgan | C21: Preparation Date | D21: 46211 | E21: Reviewed By | G21: Review Date
A23: Reviewer conclusion: Passing at the testing date with limited net leverage headroom. Resolve the downside alert, confirm add-back support, and use the lender's required certificate form.
