Workbook

Sheet Start Here
A1: Monthly Financial Statement Review
A4: Client Name | B4: Northstar Components LLC
A5: Period End | B5: 46203
A6: Prepared By | B6: Taylor Morgan
A7: Review Date | B7: 46213
A8: Input Mode | B8: Paste Import
A9: Currency | B9: USD
A10: Materiality Amount | B10: 5000
A11: Materiality Percentage | B11: 0.1
A14: Workflow
A15: 1. Confirm client, period, preparer, input mode, and materiality settings.
A16: 2. Paste a trial balance or enter it manually in the blue input table.
A17: 3. Review formula-driven period and budget variances; document exceptions.
A18: 4. Print or export the Summary after all Review flags are resolved.
A22: Color | B22: Meaning
A23: Blue text | B23: Editable input
A24: Black text | B24: Formula or calculated result
A25: Amber or red | B25: Review item or failed control

Sheet Paste Import
A1: Paste Import — Monthly Trial Balance
A4: Enter or paste values in blue cells. Do not add rows beyond row 105.
A5: Statement | B5: Account Number | C5: Account Name | D5: Account Type | E5: Current Period | F5: Prior Period | G5: Budget | H5: Review Category
A6: Income Statement | B6: 4000 | C6: Product Revenue | D6: Income | E6: 245000 | F6: 210000 | G6: 230000 | H6: Revenue
A7: Income Statement | B7: 4010 | C7: Service Revenue | D7: Income | E7: 58000 | F7: 0 | G7: 45000 | H7: Revenue
A8: Income Statement | B8: 5000 | C8: Materials | D8: Cost of Goods Sold | E8: 91000 | F8: 78000 | G8: 85000 | H8: Cost of Goods Sold
A9: Income Statement | B9: 6100 | C9: Payroll | D9: Expense | E9: 73000 | F9: 68000 | G9: 70000 | H9: Operating Expense
A10: Income Statement | B10: 6200 | C10: Marketing | D10: Expense | E10: 31000 | F10: 19000 | G10: 20000 | H10: Operating Expense
A11: Income Statement | B11: 6300 | C11: Rent | D11: Expense | E11: 18000 | F11: 18000 | G11: 18000 | H11: Operating Expense
A12: Balance Sheet | B12: 1000 | C12: Operating Cash | D12: Bank | E12: 122000 | F12: 96000 | G12: 110000 | H12: Cash
A13: Balance Sheet | B13: 1100 | C13: Accounts Receivable | D13: Accounts Receivable | E13: 87000 | F13: 72000 | G13: 76000 | H13: Accounts Receivable
A14: Balance Sheet | B14: 1200 | C14: Prepaid Expenses | D14: Other Current Asset | E14: 14000 | F14: 12000 | G14: 13000 | H14: Current Assets
A15: Balance Sheet | B15: 2000 | C15: Accounts Payable | D15: Accounts Payable | E15: 62000 | F15: 51000 | G15: 55000 | H15: Accounts Payable
A16: Balance Sheet | B16: 2100 | C16: Accrued Payroll | D16: Other Current Liability | E16: 28000 | F16: 24000 | G16: 26000 | H16: Current Liabilities
A17: Balance Sheet | B17: 2200 | C17: Sales Tax Payable | D17: Other Current Liability | E17: 9000 | F17: 8000 | G17: 8500 | H17: Current Liabilities

Sheet Manual Input
A1: Manual Input — Monthly Trial Balance
A4: Enter or paste values in blue cells. Do not add rows beyond row 105.
A5: Statement | B5: Account Number | C5: Account Name | D5: Account Type | E5: Current Period | F5: Prior Period | G5: Budget | H5: Review Category
A6: Income Statement | B6: 4000 | C6: Product Revenue | D6: Income | E6: 245000 | F6: 210000 | G6: 230000 | H6: Revenue
A7: Income Statement | B7: 4010 | C7: Service Revenue | D7: Income | E7: 58000 | F7: 0 | G7: 45000 | H7: Revenue
A8: Income Statement | B8: 5000 | C8: Materials | D8: Cost of Goods Sold | E8: 91000 | F8: 78000 | G8: 85000 | H8: Cost of Goods Sold
A9: Income Statement | B9: 6100 | C9: Payroll | D9: Expense | E9: 73000 | F9: 68000 | G9: 70000 | H9: Operating Expense
A10: Income Statement | B10: 6200 | C10: Marketing | D10: Expense | E10: 31000 | F10: 19000 | G10: 20000 | H10: Operating Expense
A11: Income Statement | B11: 6300 | C11: Rent | D11: Expense | E11: 18000 | F11: 18000 | G11: 18000 | H11: Operating Expense
A12: Balance Sheet | B12: 1000 | C12: Operating Cash | D12: Bank | E12: 122000 | F12: 96000 | G12: 110000 | H12: Cash
A13: Balance Sheet | B13: 1100 | C13: Accounts Receivable | D13: Accounts Receivable | E13: 87000 | F13: 72000 | G13: 76000 | H13: Accounts Receivable
A14: Balance Sheet | B14: 1200 | C14: Prepaid Expenses | D14: Other Current Asset | E14: 14000 | F14: 12000 | G14: 13000 | H14: Current Assets
A15: Balance Sheet | B15: 2000 | C15: Accounts Payable | D15: Accounts Payable | E15: 62000 | F15: 51000 | G15: 55000 | H15: Accounts Payable
A16: Balance Sheet | B16: 2100 | C16: Accrued Payroll | D16: Other Current Liability | E16: 28000 | F16: 24000 | G16: 26000 | H16: Current Liabilities
A17: Balance Sheet | B17: 2200 | C17: Sales Tax Payable | D17: Other Current Liability | E17: 9000 | F17: 8000 | G17: 8500 | H17: Current Liabilities

Sheet Review
A1: Monthly Financial Statement Review
A4: Formula-driven comparison. Add reviewer notes only in column N.
A5: Statement | B5: Account Number | C5: Account Name | D5: Account Type | E5: Current | F5: Prior | G5: Budget | H5: Change $ | I5: Change % | J5: Budget Var $ | K5: Budget Var % | L5: Review Category | M5: Flag | N5: Notes | O5: Exception Score
A6: =IF('Start Here'!$B$8="Paste Import",'Paste Import'!A6,'Manual Input'!A6) -> Income Statement | B6: =IF('Start Here'!$B$8="Paste Import",'Paste Import'!B6,'Manual Input'!B6) -> 4000 | C6: =IF('Start Here'!$B$8="Paste Import",'Paste Import'!C6,'Manual Input'!C6) -> Product Revenue | D6: =IF('Start Here'!$B$8="Paste Import",'Paste Import'!D6,'Manual Input'!D6) -> Income | E6: =IF('Start Here'!$B$8="Paste Import",'Paste Import'!E6,'Manual Input'!E6) -> 245000 | F6: =IF('Start Here'!$B$8="Paste Import",'Paste Import'!F6,'Manual Input'!F6) -> 210000 | G6: =IF('Start Here'!$B$8="Paste Import",'Paste Import'!G6,'Manual Input'!G6) -> 230000 | H6: =IF(C6="","",E6-F6) -> 35000 | I6: =IF(C6="","",IF(F6=0,IF(E6=0,"","New"),H6/ABS(F6))) -> 0.16666667 | J6: =IF(C6="","",E6-G6) -> 15000 | K6: =IF(C6="","",IF(G6=0,IF(E6=0,"","New"),J6/ABS(G6))) -> 0.065217391 | L6: =IF('Start Here'!$B$8="Paste Import",'Paste Import'!H6,'Manual Input'!H6) -> Revenue | M6: =IF(C6="","",IF(OR(D6="",L6=""),"Incomplete",IF(OR(AND(ABS(H6)>='Start Here'!$B$10,IFERROR(ABS(I6)>='Start Here'!$B$11,TRUE)),AND(ABS(J6)>='Start Here'!$B$10,IFERROR(ABS(K6)>='Start Here'!$B$11,TRUE))),"Review","OK"))) -> Review | O6: =IF(M6="Review",ABS(H6)+ABS(J6)+ROW()/1000000,0) -> 50000
A7: =IF('Start Here'!$B$8="Paste Import",'Paste Import'!A7,'Manual Input'!A7) -> Income Statement | B7: =IF('Start Here'!$B$8="Paste Import",'Paste Import'!B7,'Manual Input'!B7) -> 4010 | C7: =IF('Start Here'!$B$8="Paste Import",'Paste Import'!C7,'Manual Input'!C7) -> Service Revenue | D7: =IF('Start Here'!$B$8="Paste Import",'Paste Import'!D7,'Manual Input'!D7) -> Income | E7: =IF('Start Here'!$B$8="Paste Import",'Paste Import'!E7,'Manual Input'!E7) -> 58000 | F7: =IF('Start Here'!$B$8="Paste Import",'Paste Import'!F7,'Manual Input'!F7) -> 0 | G7: =IF('Start Here'!$B$8="Paste Import",'Paste Import'!G7,'Manual Input'!G7) -> 45000 | H7: =IF(C7="","",E7-F7) -> 58000 | I7: =IF(C7="","",IF(F7=0,IF(E7=0,"","New"),H7/ABS(F7))) -> New | J7: =IF(C7="","",E7-G7) -> 13000 | K7: =IF(C7="","",IF(G7=0,IF(E7=0,"","New"),J7/ABS(G7))) -> 0.28888889 | L7: =IF('Start Here'!$B$8="Paste Import",'Paste Import'!H7,'Manual Input'!H7) -> Revenue | M7: =IF(C7="","",IF(OR(D7="",L7=""),"Incomplete",IF(OR(AND(ABS(H7)>='Start Here'!$B$10,IFERROR(ABS(I7)>='Start Here'!$B$11,TRUE)),AND(ABS(J7)>='Start Here'!$B$10,IFERROR(ABS(K7)>='Start Here'!$B$11,TRUE))),"Review","OK"))) -> Review | O7: =IF(M7="Review",ABS(H7)+ABS(J7)+ROW()/1000000,0) -> 71000
A8: =IF('Start Here'!$B$8="Paste Import",'Paste Import'!A8,'Manual Input'!A8) -> Income Statement | B8: =IF('Start Here'!$B$8="Paste Import",'Paste Import'!B8,'Manual Input'!B8) -> 5000 | C8: =IF('Start Here'!$B$8="Paste Import",'Paste Import'!C8,'Manual Input'!C8) -> Materials | D8: =IF('Start Here'!$B$8="Paste Import",'Paste Import'!D8,'Manual Input'!D8) -> Cost of Goods Sold | E8: =IF('Start Here'!$B$8="Paste Import",'Paste Import'!E8,'Manual Input'!E8) -> 91000 | F8: =IF('Start Here'!$B$8="Paste Import",'Paste Import'!F8,'Manual Input'!F8) -> 78000 | G8: =IF('Start Here'!$B$8="Paste Import",'Paste Import'!G8,'Manual Input'!G8) -> 85000 | H8: =IF(C8="","",E8-F8) -> 13000 | I8: =IF(C8="","",IF(F8=0,IF(E8=0,"","New"),H8/ABS(F8))) -> 0.16666667 | J8: =IF(C8="","",E8-G8) -> 6000 | K8: =IF(C8="","",IF(G8=0,IF(E8=0,"","New"),J8/ABS(G8))) -> 0.070588235 | L8: =IF('Start Here'!$B$8="Paste Import",'Paste Import'!H8,'Manual Input'!H8) -> Cost of Goods Sold | M8: =IF(C8="","",IF(OR(D8="",L8=""),"Incomplete",IF(OR(AND(ABS(H8)>='Start Here'!$B$10,IFERROR(ABS(I8)>='Start Here'!$B$11,TRUE)),AND(ABS(J8)>='Start Here'!$B$10,IFERROR(ABS(K8)>='Start Here'!$B$11,TRUE))),"Review","OK"))) -> Review | O8: =IF(M8="Review",ABS(H8)+ABS(J8)+ROW()/1000000,0) -> 19000
A9: =IF('Start Here'!$B$8="Paste Import",'Paste Import'!A9,'Manual Input'!A9) -> Income Statement | B9: =IF('Start Here'!$B$8="Paste Import",'Paste Import'!B9,'Manual Input'!B9) -> 6100 | C9: =IF('Start Here'!$B$8="Paste Import",'Paste Import'!C9,'Manual Input'!C9) -> Payroll | D9: =IF('Start Here'!$B$8="Paste Import",'Paste Import'!D9,'Manual Input'!D9) -> Expense | E9: =IF('Start Here'!$B$8="Paste Import",'Paste Import'!E9,'Manual Input'!E9) -> 73000 | F9: =IF('Start Here'!$B$8="Paste Import",'Paste Import'!F9,'Manual Input'!F9) -> 68000 | G9: =IF('Start Here'!$B$8="Paste Import",'Paste Import'!G9,'Manual Input'!G9) -> 70000 | H9: =IF(C9="","",E9-F9) -> 5000 | I9: =IF(C9="","",IF(F9=0,IF(E9=0,"","New"),H9/ABS(F9))) -> 0.073529412 | J9: =IF(C9="","",E9-G9) -> 3000 | K9: =IF(C9="","",IF(G9=0,IF(E9=0,"","New"),J9/ABS(G9))) -> 0.042857143 | L9: =IF('Start Here'!$B$8="Paste Import",'Paste Import'!H9,'Manual Input'!H9) -> Operating Expense | M9: =IF(C9="","",IF(OR(D9="",L9=""),"Incomplete",IF(OR(AND(ABS(H9)>='Start Here'!$B$10,IFERROR(ABS(I9)>='Start Here'!$B$11,TRUE)),AND(ABS(J9)>='Start Here'!$B$10,IFERROR(ABS(K9)>='Start Here'!$B$11,TRUE))),"Review","OK"))) -> OK | O9: =IF(M9="Review",ABS(H9)+ABS(J9)+ROW()/1000000,0) -> 0
A10: =IF('Start Here'!$B$8="Paste Import",'Paste Import'!A10,'Manual Input'!A10) -> Income Statement | B10: =IF('Start Here'!$B$8="Paste Import",'Paste Import'!B10,'Manual Input'!B10) -> 6200 | C10: =IF('Start Here'!$B$8="Paste Import",'Paste Import'!C10,'Manual Input'!C10) -> Marketing | D10: =IF('Start Here'!$B$8="Paste Import",'Paste Import'!D10,'Manual Input'!D10) -> Expense | E10: =IF('Start Here'!$B$8="Paste Import",'Paste Import'!E10,'Manual Input'!E10) -> 31000 | F10: =IF('Start Here'!$B$8="Paste Import",'Paste Import'!F10,'Manual Input'!F10) -> 19000 | G10: =IF('Start Here'!$B$8="Paste Import",'Paste Import'!G10,'Manual Input'!G10) -> 20000 | H10: =IF(C10="","",E10-F10) -> 12000 | I10: =IF(C10="","",IF(F10=0,IF(E10=0,"","New"),H10/ABS(F10))) -> 0.63157895 | J10: =IF(C10="","",E10-G10) -> 11000 | K10: =IF(C10="","",IF(G10=0,IF(E10=0,"","New"),J10/ABS(G10))) -> 0.55 | L10: =IF('Start Here'!$B$8="Paste Import",'Paste Import'!H10,'Manual Input'!H10) -> Operating Expense | M10: =IF(C10="","",IF(OR(D10="",L10=""),"Incomplete",IF(OR(AND(ABS(H10)>='Start Here'!$B$10,IFERROR(ABS(I10)>='Start Here'!$B$11,TRUE)),AND(ABS(J10)>='Start Here'!$B$10,IFERROR(ABS(K10)>='Start Here'!$B$11,TRUE))),"Review","OK"))) -> Review | O10: =IF(M10="Review",ABS(H10)+ABS(J10)+ROW()/1000000,0) -> 23000
A11: =IF('Start Here'!$B$8="Paste Import",'Paste Import'!A11,'Manual Input'!A11) -> Income Statement | B11: =IF('Start Here'!$B$8="Paste Import",'Paste Import'!B11,'Manual Input'!B11) -> 6300 | C11: =IF('Start Here'!$B$8="Paste Import",'Paste Import'!C11,'Manual Input'!C11) -> Rent | D11: =IF('Start Here'!$B$8="Paste Import",'Paste Import'!D11,'Manual Input'!D11) -> Expense | E11: =IF('Start Here'!$B$8="Paste Import",'Paste Import'!E11,'Manual Input'!E11) -> 18000 | F11: =IF('Start Here'!$B$8="Paste Import",'Paste Import'!F11,'Manual Input'!F11) -> 18000 | G11: =IF('Start Here'!$B$8="Paste Import",'Paste Import'!G11,'Manual Input'!G11) -> 18000 | H11: =IF(C11="","",E11-F11) -> 0 | I11: =IF(C11="","",IF(F11=0,IF(E11=0,"","New"),H11/ABS(F11))) -> 0 | J11: =IF(C11="","",E11-G11) -> 0 | K11: =IF(C11="","",IF(G11=0,IF(E11=0,"","New"),J11/ABS(G11))) -> 0 | L11: =IF('Start Here'!$B$8="Paste Import",'Paste Import'!H11,'Manual Input'!H11) -> Operating Expense | M11: =IF(C11="","",IF(OR(D11="",L11=""),"Incomplete",IF(OR(AND(ABS(H11)>='Start Here'!$B$10,IFERROR(ABS(I11)>='Start Here'!$B$11,TRUE)),AND(ABS(J11)>='Start Here'!$B$10,IFERROR(ABS(K11)>='Start Here'!$B$11,TRUE))),"Review","OK"))) -> OK | O11: =IF(M11="Review",ABS(H11)+ABS(J11)+ROW()/1000000,0) -> 0
A12: =IF('Start Here'!$B$8="Paste Import",'Paste Import'!A12,'Manual Input'!A12) -> Balance Sheet | B12: =IF('Start Here'!$B$8="Paste Import",'Paste Import'!B12,'Manual Input'!B12) -> 1000 | C12: =IF('Start Here'!$B$8="Paste Import",'Paste Import'!C12,'Manual Input'!C12) -> Operating Cash | D12: =IF('Start Here'!$B$8="Paste Import",'Paste Import'!D12,'Manual Input'!D12) -> Bank | E12: =IF('Start Here'!$B$8="Paste Import",'Paste Import'!E12,'Manual Input'!E12) -> 122000 | F12: =IF('Start Here'!$B$8="Paste Import",'Paste Import'!F12,'Manual Input'!F12) -> 96000 | G12: =IF('Start Here'!$B$8="Paste Import",'Paste Import'!G12,'Manual Input'!G12) -> 110000 | H12: =IF(C12="","",E12-F12) -> 26000 | I12: =IF(C12="","",IF(F12=0,IF(E12=0,"","New"),H12/ABS(F12))) -> 0.27083333 | J12: =IF(C12="","",E12-G12) -> 12000 | K12: =IF(C12="","",IF(G12=0,IF(E12=0,"","New"),J12/ABS(G12))) -> 0.10909091 | L12: =IF('Start Here'!$B$8="Paste Import",'Paste Import'!H12,'Manual Input'!H12) -> Cash | M12: =IF(C12="","",IF(OR(D12="",L12=""),"Incomplete",IF(OR(AND(ABS(H12)>='Start Here'!$B$10,IFERROR(ABS(I12)>='Start Here'!$B$11,TRUE)),AND(ABS(J12)>='Start Here'!$B$10,IFERROR(ABS(K12)>='Start Here'!$B$11,TRUE))),"Review","OK"))) -> Review | O12: =IF(M12="Review",ABS(H12)+ABS(J12)+ROW()/1000000,0) -> 38000
A13: =IF('Start Here'!$B$8="Paste Import",'Paste Import'!A13,'Manual Input'!A13) -> Balance Sheet | B13: =IF('Start Here'!$B$8="Paste Import",'Paste Import'!B13,'Manual Input'!B13) -> 1100 | C13: =IF('Start Here'!$B$8="Paste Import",'Paste Import'!C13,'Manual Input'!C13) -> Accounts Receivable | D13: =IF('Start Here'!$B$8="Paste Import",'Paste Import'!D13,'Manual Input'!D13) -> Accounts Receivable | E13: =IF('Start Here'!$B$8="Paste Import",'Paste Import'!E13,'Manual Input'!E13) -> 87000 | F13: =IF('Start Here'!$B$8="Paste Import",'Paste Import'!F13,'Manual Input'!F13) -> 72000 | G13: =IF('Start Here'!$B$8="Paste Import",'Paste Import'!G13,'Manual Input'!G13) -> 76000 | H13: =IF(C13="","",E13-F13) -> 15000 | I13: =IF(C13="","",IF(F13=0,IF(E13=0,"","New"),H13/ABS(F13))) -> 0.20833333 | J13: =IF(C13="","",E13-G13) -> 11000 | K13: =IF(C13="","",IF(G13=0,IF(E13=0,"","New"),J13/ABS(G13))) -> 0.14473684 | L13: =IF('Start Here'!$B$8="Paste Import",'Paste Import'!H13,'Manual Input'!H13) -> Accounts Receivable | M13: =IF(C13="","",IF(OR(D13="",L13=""),"Incomplete",IF(OR(AND(ABS(H13)>='Start Here'!$B$10,IFERROR(ABS(I13)>='Start Here'!$B$11,TRUE)),AND(ABS(J13)>='Start Here'!$B$10,IFERROR(ABS(K13)>='Start Here'!$B$11,TRUE))),"Review","OK"))) -> Review | O13: =IF(M13="Review",ABS(H13)+ABS(J13)+ROW()/1000000,0) -> 26000
A14: =IF('Start Here'!$B$8="Paste Import",'Paste Import'!A14,'Manual Input'!A14) -> Balance Sheet | B14: =IF('Start Here'!$B$8="Paste Import",'Paste Import'!B14,'Manual Input'!B14) -> 1200 | C14: =IF('Start Here'!$B$8="Paste Import",'Paste Import'!C14,'Manual Input'!C14) -> Prepaid Expenses | D14: =IF('Start Here'!$B$8="Paste Import",'Paste Import'!D14,'Manual Input'!D14) -> Other Current Asset | E14: =IF('Start Here'!$B$8="Paste Import",'Paste Import'!E14,'Manual Input'!E14) -> 14000 | F14: =IF('Start Here'!$B$8="Paste Import",'Paste Import'!F14,'Manual Input'!F14) -> 12000 | G14: =IF('Start Here'!$B$8="Paste Import",'Paste Import'!G14,'Manual Input'!G14) -> 13000 | H14: =IF(C14="","",E14-F14) -> 2000 | I14: =IF(C14="","",IF(F14=0,IF(E14=0,"","New"),H14/ABS(F14))) -> 0.16666667 | J14: =IF(C14="","",E14-G14) -> 1000 | K14: =IF(C14="","",IF(G14=0,IF(E14=0,"","New"),J14/ABS(G14))) -> 0.076923077 | L14: =IF('Start Here'!$B$8="Paste Import",'Paste Import'!H14,'Manual Input'!H14) -> Current Assets | M14: =IF(C14="","",IF(OR(D14="",L14=""),"Incomplete",IF(OR(AND(ABS(H14)>='Start Here'!$B$10,IFERROR(ABS(I14)>='Start Here'!$B$11,TRUE)),AND(ABS(J14)>='Start Here'!$B$10,IFERROR(ABS(K14)>='Start Here'!$B$11,TRUE))),"Review","OK"))) -> OK | O14: =IF(M14="Review",ABS(H14)+ABS(J14)+ROW()/1000000,0) -> 0
A15: =IF('Start Here'!$B$8="Paste Import",'Paste Import'!A15,'Manual Input'!A15) -> Balance Sheet | B15: =IF('Start Here'!$B$8="Paste Import",'Paste Import'!B15,'Manual Input'!B15) -> 2000 | C15: =IF('Start Here'!$B$8="Paste Import",'Paste Import'!C15,'Manual Input'!C15) -> Accounts Payable | D15: =IF('Start Here'!$B$8="Paste Import",'Paste Import'!D15,'Manual Input'!D15) -> Accounts Payable | E15: =IF('Start Here'!$B$8="Paste Import",'Paste Import'!E15,'Manual Input'!E15) -> 62000 | F15: =IF('Start Here'!$B$8="Paste Import",'Paste Import'!F15,'Manual Input'!F15) -> 51000 | G15: =IF('Start Here'!$B$8="Paste Import",'Paste Import'!G15,'Manual Input'!G15) -> 55000 | H15: =IF(C15="","",E15-F15) -> 11000 | I15: =IF(C15="","",IF(F15=0,IF(E15=0,"","New"),H15/ABS(F15))) -> 0.21568627 | J15: =IF(C15="","",E15-G15) -> 7000 | K15: =IF(C15="","",IF(G15=0,IF(E15=0,"","New"),J15/ABS(G15))) -> 0.12727273 | L15: =IF('Start Here'!$B$8="Paste Import",'Paste Import'!H15,'Manual Input'!H15) -> Accounts Payable | M15: =IF(C15="","",IF(OR(D15="",L15=""),"Incomplete",IF(OR(AND(ABS(H15)>='Start Here'!$B$10,IFERROR(ABS(I15)>='Start Here'!$B$11,TRUE)),AND(ABS(J15)>='Start Here'!$B$10,IFERROR(ABS(K15)>='Start Here'!$B$11,TRUE))),"Review","OK"))) -> Review | O15: =IF(M15="Review",ABS(H15)+ABS(J15)+ROW()/1000000,0) -> 18000
A16: =IF('Start Here'!$B$8="Paste Import",'Paste Import'!A16,'Manual Input'!A16) -> Balance Sheet | B16: =IF('Start Here'!$B$8="Paste Import",'Paste Import'!B16,'Manual Input'!B16) -> 2100 | C16: =IF('Start Here'!$B$8="Paste Import",'Paste Import'!C16,'Manual Input'!C16) -> Accrued Payroll | D16: =IF('Start Here'!$B$8="Paste Import",'Paste Import'!D16,'Manual Input'!D16) -> Other Current Liability | E16: =IF('Start Here'!$B$8="Paste Import",'Paste Import'!E16,'Manual Input'!E16) -> 28000 | F16: =IF('Start Here'!$B$8="Paste Import",'Paste Import'!F16,'Manual Input'!F16) -> 24000 | G16: =IF('Start Here'!$B$8="Paste Import",'Paste Import'!G16,'Manual Input'!G16) -> 26000 | H16: =IF(C16="","",E16-F16) -> 4000 | I16: =IF(C16="","",IF(F16=0,IF(E16=0,"","New"),H16/ABS(F16))) -> 0.16666667 | J16: =IF(C16="","",E16-G16) -> 2000 | K16: =IF(C16="","",IF(G16=0,IF(E16=0,"","New"),J16/ABS(G16))) -> 0.076923077 | L16: =IF('Start Here'!$B$8="Paste Import",'Paste Import'!H16,'Manual Input'!H16) -> Current Liabilities | M16: =IF(C16="","",IF(OR(D16="",L16=""),"Incomplete",IF(OR(AND(ABS(H16)>='Start Here'!$B$10,IFERROR(ABS(I16)>='Start Here'!$B$11,TRUE)),AND(ABS(J16)>='Start Here'!$B$10,IFERROR(ABS(K16)>='Start Here'!$B$11,TRUE))),"Review","OK"))) -> OK | O16: =IF(M16="Review",ABS(H16)+ABS(J16)+ROW()/1000000,0) -> 0
A17: =IF('Start Here'!$B$8="Paste Import",'Paste Import'!A17,'Manual Input'!A17) -> Balance Sheet | B17: =IF('Start Here'!$B$8="Paste Import",'Paste Import'!B17,'Manual Input'!B17) -> 2200 | C17: =IF('Start Here'!$B$8="Paste Import",'Paste Import'!C17,'Manual Input'!C17) -> Sales Tax Payable | D17: =IF('Start Here'!$B$8="Paste Import",'Paste Import'!D17,'Manual Input'!D17) -> Other Current Liability | E17: =IF('Start Here'!$B$8="Paste Import",'Paste Import'!E17,'Manual Input'!E17) -> 9000 | F17: =IF('Start Here'!$B$8="Paste Import",'Paste Import'!F17,'Manual Input'!F17) -> 8000 | G17: =IF('Start Here'!$B$8="Paste Import",'Paste Import'!G17,'Manual Input'!G17) -> 8500 | H17: =IF(C17="","",E17-F17) -> 1000 | I17: =IF(C17="","",IF(F17=0,IF(E17=0,"","New"),H17/ABS(F17))) -> 0.125 | J17: =IF(C17="","",E17-G17) -> 500 | K17: =IF(C17="","",IF(G17=0,IF(E17=0,"","New"),J17/ABS(G17))) -> 0.058823529 | L17: =IF('Start Here'!$B$8="Paste Import",'Paste Import'!H17,'Manual Input'!H17) -> Current Liabilities | M17: =IF(C17="","",IF(OR(D17="",L17=""),"Incomplete",IF(OR(AND(ABS(H17)>='Start Here'!$B$10,IFERROR(ABS(I17)>='Start Here'!$B$11,TRUE)),AND(ABS(J17)>='Start Here'!$B$10,IFERROR(ABS(K17)>='Start Here'!$B$11,TRUE))),"Review","OK"))) -> OK | O17: =IF(M17="Review",ABS(H17)+ABS(J17)+ROW()/1000000,0) -> 0
... A105: =IF('Start Here'!$B$8="Paste Import",'Paste Import'!A105,'Manual Input'!A105) | B105: =IF('Start Here'!$B$8="Paste Import",'Paste Import'!B105,'Manual Input'!B105) | C105: =IF('Start Here'!$B$8="Paste Import",'Paste Import'!C105,'Manual Input'!C105) | D105: =IF('Start Here'!$B$8="Paste Import",'Paste Import'!D105,'Manual Input'!D105) | E105: =IF('Start Here'!$B$8="Paste Import",'Paste Import'!E105,'Manual Input'!E105) | F105: =IF('Start Here'!$B$8="Paste Import",'Paste Import'!F105,'Manual Input'!F105) | G105: =IF('Start Here'!$B$8="Paste Import",'Paste Import'!G105,'Manual Input'!G105) | H105: =IF(C105="","",E105-F105) | I105: =IF(C105="","",IF(F105=0,IF(E105=0,"","New"),H105/ABS(F105))) | J105: =IF(C105="","",E105-G105) | K105: =IF(C105="","",IF(G105=0,IF(E105=0,"","New"),J105/ABS(G105))) | L105: =IF('Start Here'!$B$8="Paste Import",'Paste Import'!H105,'Manual Input'!H105) | M105: =IF(C105="","",IF(OR(D105="",L105=""),"Incomplete",IF(OR(AND(ABS(H105)>='Start Here'!$B$10,IFERROR(ABS(I105)>='Start Here'!$B$11,TRUE)),AND(ABS(J105)>='Start Here'!$B$10,IFERROR(ABS(K105)>='Start Here'!$B$11,TRUE))),"Review","OK"))) | O105: =IF(M105="Review",ABS(H105)+ABS(J105)+ROW()/1000000,0) -> 0

Sheet Summary
A1: Monthly Financial Review — Executive Summary
A3: Decision-ready KPIs and the five largest exceptions
A5: Client | B5: ='Start Here'!B4 -> Northstar Components LLC | C5: Period End | D5: ='Start Here'!B5 -> 2026-06-30 | E5: Prepared By | F5: ='Start Here'!B6 -> Taylor Morgan | G5: Status | H5: =IF(D12=0,"Complete","Review") -> Review
A8: Revenue | C8: Gross Profit | E8: Operating Income | G8: Net Income
A9: =SUMIFS('Review'!$E$6:$E$105,'Review'!$L$6:$L$105,"Revenue") -> 303000 | C9: =B8-SUMIFS('Review'!$E$6:$E$105,'Review'!$L$6:$L$105,"Cost of Goods Sold") -> 212000 | E9: =D8-SUMIFS('Review'!$E$6:$E$105,'Review'!$L$6:$L$105,"Operating Expense") -> 90000 | G9: =F8+SUMIFS('Review'!$E$6:$E$105,'Review'!$L$6:$L$105,"Other Income")-SUMIFS('Review'!$E$6:$E$105,'Review'!$L$6:$L$105,"Other Expense") -> 90000
A11: Working Capital | C11: Exception Count
A12: =SUMIFS('Review'!$E$6:$E$105,'Review'!$L$6:$L$105,"Cash")+SUMIFS('Review'!$E$6:$E$105,'Review'!$L$6:$L$105,"Accounts Receivable")+SUMIFS('Review'!$E$6:$E$105,'Review'!$L$6:$L$105,"Current Assets")-SUMIFS('Review'!$E$6:$E$105,'Review'!$L$6:$L$105,"Accounts Payable")-SUMIFS('Review'!$E$6:$E$105,'Review'!$L$6:$L$105,"Current Liabilities") -> 124000 | C12: =COUNTIF('Review'!$M$6:$M$105,"Review")+COUNTIF('Review'!$M$6:$M$105,"Incomplete") -> 7
A14: Top Five Exceptions
A15: Rank | B15: Account | C15: Category | D15: Current | E15: Change $ | F15: Budget Var $ | G15: Flag | H15: Reviewer Notes
A16: 1 | B16: =IFERROR(INDEX('Review'!$C$6:$C$105,MATCH(LARGE('Review'!$O$6:$O$105,1),'Review'!$O$6:$O$105,0)),"") -> Service Revenue | C16: =IFERROR(INDEX('Review'!$L$6:$L$105,MATCH(LARGE('Review'!$O$6:$O$105,1),'Review'!$O$6:$O$105,0)),"") -> Revenue | D16: =IFERROR(INDEX('Review'!$E$6:$E$105,MATCH(LARGE('Review'!$O$6:$O$105,1),'Review'!$O$6:$O$105,0)),"") -> 58000 | E16: =IFERROR(INDEX('Review'!$H$6:$H$105,MATCH(LARGE('Review'!$O$6:$O$105,1),'Review'!$O$6:$O$105,0)),"") -> 58000 | F16: =IFERROR(INDEX('Review'!$J$6:$J$105,MATCH(LARGE('Review'!$O$6:$O$105,1),'Review'!$O$6:$O$105,0)),"") -> 13000 | G16: =IFERROR(INDEX('Review'!$M$6:$M$105,MATCH(LARGE('Review'!$O$6:$O$105,1),'Review'!$O$6:$O$105,0)),"") -> Review | H16: =IFERROR(INDEX('Review'!$N$6:$N$105,MATCH(LARGE('Review'!$O$6:$O$105,1),'Review'!$O$6:$O$105,0)),"")
A17: 2 | B17: =IFERROR(INDEX('Review'!$C$6:$C$105,MATCH(LARGE('Review'!$O$6:$O$105,2),'Review'!$O$6:$O$105,0)),"") -> Product Revenue | C17: =IFERROR(INDEX('Review'!$L$6:$L$105,MATCH(LARGE('Review'!$O$6:$O$105,2),'Review'!$O$6:$O$105,0)),"") -> Revenue | D17: =IFERROR(INDEX('Review'!$E$6:$E$105,MATCH(LARGE('Review'!$O$6:$O$105,2),'Review'!$O$6:$O$105,0)),"") -> 245000 | E17: =IFERROR(INDEX('Review'!$H$6:$H$105,MATCH(LARGE('Review'!$O$6:$O$105,2),'Review'!$O$6:$O$105,0)),"") -> 35000 | F17: =IFERROR(INDEX('Review'!$J$6:$J$105,MATCH(LARGE('Review'!$O$6:$O$105,2),'Review'!$O$6:$O$105,0)),"") -> 15000 | G17: =IFERROR(INDEX('Review'!$M$6:$M$105,MATCH(LARGE('Review'!$O$6:$O$105,2),'Review'!$O$6:$O$105,0)),"") -> Review | H17: =IFERROR(INDEX('Review'!$N$6:$N$105,MATCH(LARGE('Review'!$O$6:$O$105,2),'Review'!$O$6:$O$105,0)),"")
A18: 3 | B18: =IFERROR(INDEX('Review'!$C$6:$C$105,MATCH(LARGE('Review'!$O$6:$O$105,3),'Review'!$O$6:$O$105,0)),"") -> Operating Cash | C18: =IFERROR(INDEX('Review'!$L$6:$L$105,MATCH(LARGE('Review'!$O$6:$O$105,3),'Review'!$O$6:$O$105,0)),"") -> Cash | D18: =IFERROR(INDEX('Review'!$E$6:$E$105,MATCH(LARGE('Review'!$O$6:$O$105,3),'Review'!$O$6:$O$105,0)),"") -> 122000 | E18: =IFERROR(INDEX('Review'!$H$6:$H$105,MATCH(LARGE('Review'!$O$6:$O$105,3),'Review'!$O$6:$O$105,0)),"") -> 26000 | F18: =IFERROR(INDEX('Review'!$J$6:$J$105,MATCH(LARGE('Review'!$O$6:$O$105,3),'Review'!$O$6:$O$105,0)),"") -> 12000 | G18: =IFERROR(INDEX('Review'!$M$6:$M$105,MATCH(LARGE('Review'!$O$6:$O$105,3),'Review'!$O$6:$O$105,0)),"") -> Review | H18: =IFERROR(INDEX('Review'!$N$6:$N$105,MATCH(LARGE('Review'!$O$6:$O$105,3),'Review'!$O$6:$O$105,0)),"")
A19: 4 | B19: =IFERROR(INDEX('Review'!$C$6:$C$105,MATCH(LARGE('Review'!$O$6:$O$105,4),'Review'!$O$6:$O$105,0)),"") -> Accounts Receivable | C19: =IFERROR(INDEX('Review'!$L$6:$L$105,MATCH(LARGE('Review'!$O$6:$O$105,4),'Review'!$O$6:$O$105,0)),"") -> Accounts Receivable | D19: =IFERROR(INDEX('Review'!$E$6:$E$105,MATCH(LARGE('Review'!$O$6:$O$105,4),'Review'!$O$6:$O$105,0)),"") -> 87000 | E19: =IFERROR(INDEX('Review'!$H$6:$H$105,MATCH(LARGE('Review'!$O$6:$O$105,4),'Review'!$O$6:$O$105,0)),"") -> 15000 | F19: =IFERROR(INDEX('Review'!$J$6:$J$105,MATCH(LARGE('Review'!$O$6:$O$105,4),'Review'!$O$6:$O$105,0)),"") -> 11000 | G19: =IFERROR(INDEX('Review'!$M$6:$M$105,MATCH(LARGE('Review'!$O$6:$O$105,4),'Review'!$O$6:$O$105,0)),"") -> Review | H19: =IFERROR(INDEX('Review'!$N$6:$N$105,MATCH(LARGE('Review'!$O$6:$O$105,4),'Review'!$O$6:$O$105,0)),"")
A20: 5 | B20: =IFERROR(INDEX('Review'!$C$6:$C$105,MATCH(LARGE('Review'!$O$6:$O$105,5),'Review'!$O$6:$O$105,0)),"") -> Marketing | C20: =IFERROR(INDEX('Review'!$L$6:$L$105,MATCH(LARGE('Review'!$O$6:$O$105,5),'Review'!$O$6:$O$105,0)),"") -> Operating Expense | D20: =IFERROR(INDEX('Review'!$E$6:$E$105,MATCH(LARGE('Review'!$O$6:$O$105,5),'Review'!$O$6:$O$105,0)),"") -> 31000 | E20: =IFERROR(INDEX('Review'!$H$6:$H$105,MATCH(LARGE('Review'!$O$6:$O$105,5),'Review'!$O$6:$O$105,0)),"") -> 12000 | F20: =IFERROR(INDEX('Review'!$J$6:$J$105,MATCH(LARGE('Review'!$O$6:$O$105,5),'Review'!$O$6:$O$105,0)),"") -> 11000 | G20: =IFERROR(INDEX('Review'!$M$6:$M$105,MATCH(LARGE('Review'!$O$6:$O$105,5),'Review'!$O$6:$O$105,0)),"") -> Review | H20: =IFERROR(INDEX('Review'!$N$6:$N$105,MATCH(LARGE('Review'!$O$6:$O$105,5),'Review'!$O$6:$O$105,0)),"")

Sheet Lists
A1: Statement | B1: Account Type | C1: Review Category | D1: Input Mode
A2: Income Statement | B2: Income | C2: Revenue | D2: Paste Import
A3: Balance Sheet | B3: Cost of Goods Sold | C3: Cost of Goods Sold | D3: Manual Input
B4: Expense | C4: Operating Expense
B5: Bank | C5: Other Income
B6: Accounts Receivable | C6: Other Expense
B7: Other Current Asset | C7: Cash
B8: Accounts Payable | C8: Accounts Receivable
B9: Other Current Liability | C9: Current Assets
B10: Other | C10: Accounts Payable
C11: Current Liabilities
C12: Other
