Workbook

Sheet Instructions
A1: POS Daily Sales Reconciliation Tracker (Toast/Square)
A3: The problem
A4: Bank deposits almost never equal your POS sales for the day. Processors like Toast and Square net their fees out of the deposit, tips ride along with card batches, settlement lags 1 to 2 business days, and refunds, gift card sales, and cash all move independently of the card batch. If you book deposits straight to revenue, sales are understated by the fees and your books drift from the POS report.
A6: How to use this tracker
A7: 1. Daily Sales sheet: enter one row per day per location, straight from your Toast or Square daily summary. Fill only the light yellow input cells (Date through Processing Fees).
A8: 2. Expected Net Deposit is computed for you: Gross Card Sales + Tips Collected - Refunds - Processing Fees. That is what the processor should actually wire to your bank.
A9: 3. Total Daily Revenue is also computed: Gross Card Sales + Cash Sales + Gift Cards Sold - Refunds. Note this is a cash-in view, not GAAP revenue: gift cards sold are a liability until redeemed, and sales tax collected is included in the gross figures until you remit it.
A10: 4. Deposit Matching sheet: enter each bank deposit as it lands (light yellow cells), note which sales dates it covers, and point Expected Amount at the matching Expected Net Deposit cell(s) on Daily Sales.
A11: 5. Difference shows deposit minus expected for that batch. Running Clearing Balance carries prior balance + expected - deposit, mirroring an undeposited funds (clearing) account.
A13: Reading the results
A14: Because settlement lags 1 to 2 business days, the clearing balance on your books should hover near 1 to 2 days of card sales at any point in time. A clearing balance that keeps growing means deposits are not being matched to sales days: missed entries, an unrecorded fee change, or a batch that never settled. Chase any Difference larger than a few dollars the same week, while the batch detail is still easy to pull from the POS.
A16: Worked example
... A19: Input cells are light yellow. Never type over the white formula cells.

Sheet Daily Sales
A1: Date | B1: Location | C1: Gross Card Sales | D1: Cash Sales | E1: Tips Collected | F1: Gift Cards Sold | G1: Gift Cards Redeemed | H1: Refunds | I1: Sales Tax Collected | J1: Processing Fees | K1: Expected Net Deposit | L1: Total Daily Revenue
A2: 46209 | B2: Main Street | C2: 2480 | D2: 310 | E2: 372 | F2: 50 | G2: 25 | H2: 42 | I2: 205 | J2: 79.86 | K2: =C2+E2-H2-J2 | L2: =C2+D2+F2-H2
A3: 46210 | B3: Main Street | C3: 2315 | D3: 285 | E3: 347.25 | F3: 0 | G3: 40 | H3: 0 | I3: 191 | J3: 74.55 | K3: =C3+E3-H3-J3 | L3: =C3+D3+F3-H3
A4: 46211 | B4: Main Street | C4: 2640 | D4: 330 | E4: 396 | F4: 100 | G4: 30 | H4: 65 | I4: 218 | J4: 85.01 | K4: =C4+E4-H4-J4 | L4: =C4+D4+F4-H4
A5: 46212 | B5: Main Street | C5: 2895 | D5: 360 | E5: 434.25 | F5: 25 | G5: 55 | H5: 38 | I5: 239 | J5: 93.22 | K5: =C5+E5-H5-J5 | L5: =C5+D5+F5-H5
A6: 46213 | B6: Main Street | C6: 4120 | D6: 515 | E6: 618 | F6: 150 | G6: 70 | H6: 92 | I6: 340 | J6: 132.66 | K6: =C6+E6-H6-J6 | L6: =C6+D6+F6-H6
A7: 46214 | B7: Main Street | C7: 4560 | D7: 570 | E7: 684 | F7: 200 | G7: 85 | H7: 110 | I7: 376 | J7: 146.83 | K7: =C7+E7-H7-J7 | L7: =C7+D7+F7-H7
A8: 46215 | B8: Main Street | C8: 3380 | D8: 425 | E8: 507 | F8: 75 | G8: 60 | H8: 54 | I8: 279 | J8: 108.84 | K8: =C8+E8-H8-J8 | L8: =C8+D8+F8-H8
A9: TOTALS | C9: =SUM(C2:C8) | D9: =SUM(D2:D8) | E9: =SUM(E2:E8) | F9: =SUM(F2:F8) | G9: =SUM(G2:G8) | H9: =SUM(H2:H8) | I9: =SUM(I2:I8) | J9: =SUM(J2:J8) | ... L9: =SUM(L2:L8)

Sheet Deposit Matching
A1: Deposit Date | B1: Bank Deposit Amount | C1: Matched Sales Dates | D1: Expected Amount | E1: Difference | F1: Running Clearing Balance
A2: 46211 | B2: 2730.14 | C2: Jul 6 | D2: ='Daily Sales'!K2 | E2: =B2-D2 | F2: =D2-B2
A3: 46212 | B3: 2587.7 | C3: Jul 7 | D3: ='Daily Sales'!K3 | E3: =B3-D3 | F3: =F2+D3-B3
A4: 46213 | B4: 2867.49 | C4: Jul 8 | D4: ='Daily Sales'!K4 | E4: =B4-D4 | F4: =F3+D4-B4
A5: 46216 | B5: 3198.03 | C5: Jul 9 | D5: ='Daily Sales'!K5 | E5: =B5-D5 | F5: =F4+D5-B5
A6: 46217 | B6: 4513.34 | C6: Jul 10 | D6: ='Daily Sales'!K6 | E6: =B6-D6 | F6: =F5+D6-B6
A7: 46218 | B7: 8711.33 | C7: Jul 11 + Jul 12 | D7: ='Daily Sales'!K7+'Daily Sales'!K8 | E7: =B7-D7 | F7: =F6+D7-B7
