Workbook

Sheet Instructions
B2: Restaurant Menu Engineering Matrix
B3: Classify every menu item as a Star, Plowhorse, Puzzle, or Dog and know exactly what to do with each.
B5: How the method works
B6: Menu engineering (the Kasavana-Smith method) scores every item on two axes: profitability and popularity.
B7: 1. PROFITABILITY: an item is HIGH margin if its contribution margin (menu price minus food cost) is at or
B8: above the menu average. The average here is weighted: total margin dollars divided by total units sold.
B9: 2. POPULARITY: with N items on the menu, the average share of sales is 1/N. The classic 70% rule says an item
B10: is HIGH popularity if its share of units sold is at least 70% of that average share (70% x 1/N).
B11: Every item lands in one of four quadrants:
B13: STARS | C13: High margin + high popularity. Protect them: keep quality and portioning consistent, feature them prominently, resist discounting.
B14: PLOWHORSES | C14: Low margin + high popularity. They sell but earn too little: raise the price carefully, re-engineer the recipe, or cut portion cost.
B15: PUZZLES | C15: High margin + low popularity. Worth saving: promote them, rename or reposition on the menu, train servers to suggest them.
B16: DOGS | C16: Low margin + low popularity. Cut them, or replace with a stronger item. Keep only if they serve a strategic purpose.
B18: How to fill it in
B19: Only edit the YELLOW cells on the Menu Items sheet. Everything else computes automatically.
B20: 1. Item and Category: one row per menu item. Pick the category from the dropdown.
B21: 2. Menu Price: what the guest pays (before tax).
B22: 3. Food Cost: the plate cost of ingredients for one serving.
B23: 4. Units Sold: how many you sold in the analysis period. Use the same period (e.g. one month) for every item.
B24: The sheet computes contribution margin, food cost %, revenue, total margin, popularity share, and the
B25: classification for each item. The Summary sheet shows the benchmarks and totals per quadrant.
B27: Worked example (prefilled sample data)
B28: The template ships with 12 sample items. The Classic Cheeseburger earns a $10.15 margin (above the $8.82
B29: weighted average) and sells 310 of 2,065 units, a 15.0% share (above the 5.8% benchmark), so it is a Star.
B30: The Craft Lemonade sells heavily but earns only $4.10 per unit, so it is a Plowhorse. The Ribeye earns
... B33: Tip: rerun this monthly. Items drift between quadrants as costs and tastes change.

Sheet Menu Items
A1: Restaurant Menu Engineering Matrix
A2: Fill the yellow cells only. One row per menu item, same sales period for all items.
A3: Item | B3: Category | C3: Menu Price | D3: Food Cost | E3: Units Sold | F3: Contribution Margin | G3: Food Cost % | H3: Revenue | I3: Total Margin | J3: Popularity Share | K3: Classification
A4: Classic Cheeseburger | B4: Main | C4: 14.5 | D4: 4.35 | E4: 310 | F4: =IF($A4="","",$C4-$D4) | G4: =IF(OR($A4="",$C4=0),"",$D4/$C4) | H4: =IF($A4="","",$C4*$E4) | I4: =IF($A4="","",$F4*$E4) | J4: =IF(OR($A4="",$E$16=0),"",$E4/$E$16) | K4: =IF($A4="","",IF(AND($F4>=Summary!$B$4,$J4>=Summary!$B$7),"Star",IF($F4>=Summary!$B$4,"Puzzle",IF($J4>=Summary!$B$7,"Plowhorse","Dog"))))
A5: Margherita Pizza | B5: Main | C5: 15 | D5: 3.75 | E5: 280 | F5: =IF($A5="","",$C5-$D5) | G5: =IF(OR($A5="",$C5=0),"",$D5/$C5) | H5: =IF($A5="","",$C5*$E5) | I5: =IF($A5="","",$F5*$E5) | J5: =IF(OR($A5="",$E$16=0),"",$E5/$E$16) | K5: =IF($A5="","",IF(AND($F5>=Summary!$B$4,$J5>=Summary!$B$7),"Star",IF($F5>=Summary!$B$4,"Puzzle",IF($J5>=Summary!$B$7,"Plowhorse","Dog"))))
A6: Grilled Ribeye Steak | B6: Main | C6: 34 | D6: 13.6 | E6: 95 | F6: =IF($A6="","",$C6-$D6) | G6: =IF(OR($A6="",$C6=0),"",$D6/$C6) | H6: =IF($A6="","",$C6*$E6) | I6: =IF($A6="","",$F6*$E6) | J6: =IF(OR($A6="",$E$16=0),"",$E6/$E$16) | K6: =IF($A6="","",IF(AND($F6>=Summary!$B$4,$J6>=Summary!$B$7),"Star",IF($F6>=Summary!$B$4,"Puzzle",IF($J6>=Summary!$B$7,"Plowhorse","Dog"))))
A7: Chicken Caesar Salad | B7: Main | C7: 13.5 | D7: 4.05 | E7: 220 | F7: =IF($A7="","",$C7-$D7) | G7: =IF(OR($A7="",$C7=0),"",$D7/$C7) | H7: =IF($A7="","",$C7*$E7) | I7: =IF($A7="","",$F7*$E7) | J7: =IF(OR($A7="",$E$16=0),"",$E7/$E$16) | K7: =IF($A7="","",IF(AND($F7>=Summary!$B$4,$J7>=Summary!$B$7),"Star",IF($F7>=Summary!$B$4,"Puzzle",IF($J7>=Summary!$B$7,"Plowhorse","Dog"))))
A8: Fish Tacos | B8: Main | C8: 15.5 | D8: 5.4 | E8: 140 | F8: =IF($A8="","",$C8-$D8) | G8: =IF(OR($A8="",$C8=0),"",$D8/$C8) | H8: =IF($A8="","",$C8*$E8) | I8: =IF($A8="","",$F8*$E8) | J8: =IF(OR($A8="",$E$16=0),"",$E8/$E$16) | K8: =IF($A8="","",IF(AND($F8>=Summary!$B$4,$J8>=Summary!$B$7),"Star",IF($F8>=Summary!$B$4,"Puzzle",IF($J8>=Summary!$B$7,"Plowhorse","Dog"))))
A9: Truffle Mushroom Risotto | B9: Main | C9: 22 | D9: 6.6 | E9: 55 | F9: =IF($A9="","",$C9-$D9) | G9: =IF(OR($A9="",$C9=0),"",$D9/$C9) | H9: =IF($A9="","",$C9*$E9) | I9: =IF($A9="","",$F9*$E9) | J9: =IF(OR($A9="",$E$16=0),"",$E9/$E$16) | K9: =IF($A9="","",IF(AND($F9>=Summary!$B$4,$J9>=Summary!$B$7),"Star",IF($F9>=Summary!$B$4,"Puzzle",IF($J9>=Summary!$B$7,"Plowhorse","Dog"))))
A10: Loaded Nachos | B10: Appetizer | C10: 11 | D10: 3.3 | E10: 240 | F10: =IF($A10="","",$C10-$D10) | G10: =IF(OR($A10="",$C10=0),"",$D10/$C10) | H10: =IF($A10="","",$C10*$E10) | I10: =IF($A10="","",$F10*$E10) | J10: =IF(OR($A10="",$E$16=0),"",$E10/$E$16) | K10: =IF($A10="","",IF(AND($F10>=Summary!$B$4,$J10>=Summary!$B$7),"Star",IF($F10>=Summary!$B$4,"Puzzle",IF($J10>=Summary!$B$7,"Plowhorse","Dog"))))
A11: Crispy Calamari | B11: Appetizer | C11: 12.5 | D11: 5 | E11: 90 | F11: =IF($A11="","",$C11-$D11) | G11: =IF(OR($A11="",$C11=0),"",$D11/$C11) | H11: =IF($A11="","",$C11*$E11) | I11: =IF($A11="","",$F11*$E11) | J11: =IF(OR($A11="",$E$16=0),"",$E11/$E$16) | K11: =IF($A11="","",IF(AND($F11>=Summary!$B$4,$J11>=Summary!$B$7),"Star",IF($F11>=Summary!$B$4,"Puzzle",IF($J11>=Summary!$B$7,"Plowhorse","Dog"))))
A12: Garden Side Salad | B12: Appetizer | C12: 6.5 | D12: 2.6 | E12: 75 | F12: =IF($A12="","",$C12-$D12) | G12: =IF(OR($A12="",$C12=0),"",$D12/$C12) | H12: =IF($A12="","",$C12*$E12) | I12: =IF($A12="","",$F12*$E12) | J12: =IF(OR($A12="",$E$16=0),"",$E12/$E$16) | K12: =IF($A12="","",IF(AND($F12>=Summary!$B$4,$J12>=Summary!$B$7),"Star",IF($F12>=Summary!$B$4,"Puzzle",IF($J12>=Summary!$B$7,"Plowhorse","Dog"))))
A13: Chocolate Lava Cake | B13: Dessert | C13: 9 | D13: 2.25 | E13: 160 | F13: =IF($A13="","",$C13-$D13) | G13: =IF(OR($A13="",$C13=0),"",$D13/$C13) | H13: =IF($A13="","",$C13*$E13) | I13: =IF($A13="","",$F13*$E13) | J13: =IF(OR($A13="",$E$16=0),"",$E13/$E$16) | K13: =IF($A13="","",IF(AND($F13>=Summary!$B$4,$J13>=Summary!$B$7),"Star",IF($F13>=Summary!$B$4,"Puzzle",IF($J13>=Summary!$B$7,"Plowhorse","Dog"))))
A14: New York Cheesecake | B14: Dessert | C14: 8.5 | D14: 2.98 | E14: 70 | F14: =IF($A14="","",$C14-$D14) | G14: =IF(OR($A14="",$C14=0),"",$D14/$C14) | H14: =IF($A14="","",$C14*$E14) | I14: =IF($A14="","",$F14*$E14) | J14: =IF(OR($A14="",$E$16=0),"",$E14/$E$16) | K14: =IF($A14="","",IF(AND($F14>=Summary!$B$4,$J14>=Summary!$B$7),"Star",IF($F14>=Summary!$B$4,"Puzzle",IF($J14>=Summary!$B$7,"Plowhorse","Dog"))))
A15: Craft Lemonade | B15: Beverage | C15: 5 | D15: 0.9 | E15: 330 | F15: =IF($A15="","",$C15-$D15) | G15: =IF(OR($A15="",$C15=0),"",$D15/$C15) | H15: =IF($A15="","",$C15*$E15) | I15: =IF($A15="","",$F15*$E15) | J15: =IF(OR($A15="",$E$16=0),"",$E15/$E$16) | K15: =IF($A15="","",IF(AND($F15>=Summary!$B$4,$J15>=Summary!$B$7),"Star",IF($F15>=Summary!$B$4,"Puzzle",IF($J15>=Summary!$B$7,"Plowhorse","Dog"))))
A16: TOTALS / AVERAGES | E16: =SUM($E$4:$E$15) | F16: =IF($E$16=0,0,$I$16/$E$16) | G16: =IF($H$16=0,0,SUMPRODUCT($D$4:$D$15,$E$4:$E$15)/$H$16) | H16: =SUM($H$4:$H$15) | I16: =SUM($I$4:$I$15) | J16: =IF($E$16=0,0,SUM($E$4:$E$15)/$E$16)
A18: Contribution Margin in the totals row is the weighted menu average (total margin / total units).

Sheet Summary
A1: Menu Engineering Summary
A3: Benchmarks (referenced by the Classification formulas)
A4: Menu average contribution margin (weighted) | B4: =IF('Menu Items'!$E$16=0,0,'Menu Items'!$I$16/'Menu Items'!$E$16)
A5: Number of menu items | B5: =COUNTA('Menu Items'!$A$4:$A$15)
A6: Average popularity share (1 / item count) | B6: =IF($B$5=0,0,1/$B$5)
A7: 70% popularity benchmark (70% x average share) | B7: =0.7*$B$6
A8: Total units sold in period | B8: ='Menu Items'!$E$16
A10: Results by quadrant
A11: Classification | B11: Item Count | C11: Total Margin | D11: % of Total Margin
A12: Star (Protect and feature) | B12: =COUNTIF('Menu Items'!$K$4:$K$15,"Star") | C12: =SUMIF('Menu Items'!$K$4:$K$15,"Star",'Menu Items'!$I$4:$I$15) | D12: =IF('Menu Items'!$I$16=0,0,$C12/'Menu Items'!$I$16)
A13: Plowhorse (Raise price or cut plate cost) | B13: =COUNTIF('Menu Items'!$K$4:$K$15,"Plowhorse") | C13: =SUMIF('Menu Items'!$K$4:$K$15,"Plowhorse",'Menu Items'!$I$4:$I$15) | D13: =IF('Menu Items'!$I$16=0,0,$C13/'Menu Items'!$I$16)
A14: Puzzle (Promote or reposition) | B14: =COUNTIF('Menu Items'!$K$4:$K$15,"Puzzle") | C14: =SUMIF('Menu Items'!$K$4:$K$15,"Puzzle",'Menu Items'!$I$4:$I$15) | D14: =IF('Menu Items'!$I$16=0,0,$C14/'Menu Items'!$I$16)
A15: Dog (Cut or replace) | B15: =COUNTIF('Menu Items'!$K$4:$K$15,"Dog") | C15: =SUMIF('Menu Items'!$K$4:$K$15,"Dog",'Menu Items'!$I$4:$I$15) | D15: =IF('Menu Items'!$I$16=0,0,$C15/'Menu Items'!$I$16)
A16: TOTAL | B16: =SUM($B$12:$B$15) | C16: =SUM($C$12:$C$15) | D16: =IF('Menu Items'!$I$16=0,0,$C$16/'Menu Items'!$I$16)
A18: An item is HIGH margin if its contribution margin >= B4, and HIGH popularity if its share >= B7.
