Workbook

Sheet Start Here
A1: Trial Balance Review Workpaper
A4: Client Name | B4: Northstar Components LLC
A5: Period End | B5: 46203
A6: Prepared By | B6: Taylor Morgan
A7: Review Date | B7: 46213
A8: Input Mode | B8: Paste Import
A9: Currency | B9: USD
A10: Materiality Amount | B10: 5000
A11: Materiality Percentage | B11: 0.1
A14: Workflow
A15: 1. Confirm the client, period, preparer, selected input mode, and materiality settings.
A16: 2. Paste or manually enter a balanced trial balance and map each account to a review category.
A17: 3. Review mapping, sign, and materiality flags; proposed adjustments use positive debit and negative credit signs.
A18: 4. Print or export the Summary after all Review items are resolved.
A22: Color | B22: Meaning
A23: Blue text | B23: Editable input
A24: Black text | B24: Formula or calculated result
A25: Amber or red | B25: Review item or failed control

Sheet Paste Import
A1: Paste Import — Trial Balance
A4: Enter balanced debit and credit columns in blue cells. Proposed adjustments use positive debit and negative credit signs.
A5: Account Number | B5: Account Name | C5: Account Type | D5: Current Debit | E5: Current Credit | F5: Prior Debit | G5: Prior Credit | H5: Review Category | I5: Proposed Adjustment | J5: Notes
A6: 1000 | B6: Operating Cash | C6: Asset | D6: 100000 | E6: 0 | F6: 80000 | G6: 0 | H6: Cash | I6: 0 | J6: Material cash movement
A7: 1100 | B7: Accounts Receivable | C7: Asset | D7: 50000 | E7: 0 | F7: 50000 | G7: 0 | H7: Receivables | I7: 2000 | J7: Proposed debit adjustment
A8: 1200 | B8: Inventory | C8: Asset | D8: 30000 | E8: 0 | F8: 20000 | G8: 0 | H8: Inventory | I8: 0 | J8: Growth requires review
A9: 1300 | B9: Prepaid Expenses | C9: Asset | D9: 5000 | E9: 0 | F9: 5000 | G9: 0 | H9: Other | I9: 0
A10: 1500 | B10: Property and Equipment | C10: Asset | D10: 80000 | E10: 0 | F10: 75000 | G10: 0 | H10: Fixed Assets | I10: 0
A11: 1590 | B11: Accumulated Depreciation | C11: Asset | D11: 0 | E11: 25000 | F11: 0 | G11: 20000 | H11: Fixed Assets | I11: 0 | J11: Credit balance flagged by sign rule
A12: 2000 | B12: Accounts Payable | C12: Liability | D12: 0 | E12: 40000 | F12: 0 | G12: 35000 | H12: Payables | I12: 0
A13: 2100 | B13: Accrued Expenses | C13: Liability | D13: 0 | E13: 15000 | F13: 0 | G13: 10000 | H13: Payables | I13: 0
A14: 2500 | B14: Term Debt | C14: Liability | D14: 0 | E14: 60000 | F14: 0 | G14: 55000 | H14: Debt | I14: 0
A15: 3000 | B15: Members' Equity | C15: Equity | D15: 0 | E15: 110000 | F15: 0 | G15: 95000 | H15: Equity | I15: 0
A16: 4000 | B16: Product Revenue | C16: Revenue | D16: 0 | E16: 200000 | F16: 0 | G16: 180000 | H16: Revenue | I16: -2000 | J16: Proposed credit adjustment
A17: 5000 | B17: Cost of Goods Sold | C17: Expense | D17: 100000 | E17: 0 | F17: 90000 | G17: 0 | H17: Operating Expenses | I17: 0
A18: 6100 | B18: Payroll Expense | C18: Expense | D18: 60000 | E18: 0 | F18: 55000 | G18: 0 | H18: Operating Expenses | I18: 0
A19: 6200 | B19: Rent Expense | C19: Expense | D19: 20000 | E19: 0 | F19: 20000 | G19: 0 | H19: Operating Expenses | I19: 0
A20: 6900 | B20: New Compliance Expense | C20: Expense | D20: 5000 | E20: 0 | F20: 0 | G20: 0 | I20: 0 | J20: New account intentionally unmapped

Sheet Manual Input
A1: Manual Input — Trial Balance
A4: Enter balanced debit and credit columns in blue cells. Proposed adjustments use positive debit and negative credit signs.
A5: Account Number | B5: Account Name | C5: Account Type | D5: Current Debit | E5: Current Credit | F5: Prior Debit | G5: Prior Credit | H5: Review Category | I5: Proposed Adjustment | J5: Notes
A6: 1000 | B6: Operating Cash | C6: Asset | D6: 100000 | E6: 0 | F6: 80000 | G6: 0 | H6: Cash | I6: 0 | J6: Material cash movement
A7: 1100 | B7: Accounts Receivable | C7: Asset | D7: 50000 | E7: 0 | F7: 50000 | G7: 0 | H7: Receivables | I7: 2000 | J7: Proposed debit adjustment
A8: 1200 | B8: Inventory | C8: Asset | D8: 30000 | E8: 0 | F8: 20000 | G8: 0 | H8: Inventory | I8: 0 | J8: Growth requires review
A9: 1300 | B9: Prepaid Expenses | C9: Asset | D9: 5000 | E9: 0 | F9: 5000 | G9: 0 | H9: Other | I9: 0
A10: 1500 | B10: Property and Equipment | C10: Asset | D10: 80000 | E10: 0 | F10: 75000 | G10: 0 | H10: Fixed Assets | I10: 0
A11: 1590 | B11: Accumulated Depreciation | C11: Asset | D11: 0 | E11: 25000 | F11: 0 | G11: 20000 | H11: Fixed Assets | I11: 0 | J11: Credit balance flagged by sign rule
A12: 2000 | B12: Accounts Payable | C12: Liability | D12: 0 | E12: 40000 | F12: 0 | G12: 35000 | H12: Payables | I12: 0
A13: 2100 | B13: Accrued Expenses | C13: Liability | D13: 0 | E13: 15000 | F13: 0 | G13: 10000 | H13: Payables | I13: 0
A14: 2500 | B14: Term Debt | C14: Liability | D14: 0 | E14: 60000 | F14: 0 | G14: 55000 | H14: Debt | I14: 0
A15: 3000 | B15: Members' Equity | C15: Equity | D15: 0 | E15: 110000 | F15: 0 | G15: 95000 | H15: Equity | I15: 0
A16: 4000 | B16: Product Revenue | C16: Revenue | D16: 0 | E16: 200000 | F16: 0 | G16: 180000 | H16: Revenue | I16: -2000 | J16: Proposed credit adjustment
A17: 5000 | B17: Cost of Goods Sold | C17: Expense | D17: 100000 | E17: 0 | F17: 90000 | G17: 0 | H17: Operating Expenses | I17: 0
A18: 6100 | B18: Payroll Expense | C18: Expense | D18: 60000 | E18: 0 | F18: 55000 | G18: 0 | H18: Operating Expenses | I18: 0
A19: 6200 | B19: Rent Expense | C19: Expense | D19: 20000 | E19: 0 | F19: 20000 | G19: 0 | H19: Operating Expenses | I19: 0
A20: 6900 | B20: New Compliance Expense | C20: Expense | D20: 5000 | E20: 0 | F20: 0 | G20: 0 | I20: 0 | J20: New account intentionally unmapped

Sheet Review
A1: Trial Balance Review
A4: Formula-driven mapping, sign, and materiality review of the selected input mode.
A5: Account Number | B5: Account Name | C5: Account Type | D5: Current Debit | E5: Current Credit | F5: Prior Debit | G5: Prior Credit | H5: Current Net | I5: Prior Net | J5: Change $ | K5: Change % | L5: Review Category | M5: Proposed Adjustment | N5: Adjusted Balance | O5: Mapping | P5: Sign | Q5: Materiality | R5: Status | S5: Notes
A6: =IF('Start Here'!$B$8="Paste Import",'Paste Import'!A6,'Manual Input'!A6) -> 1000 | B6: =IF('Start Here'!$B$8="Paste Import",'Paste Import'!B6,'Manual Input'!B6) -> Operating Cash | C6: =IF('Start Here'!$B$8="Paste Import",'Paste Import'!C6,'Manual Input'!C6) -> Asset | D6: =IF('Start Here'!$B$8="Paste Import",'Paste Import'!D6,'Manual Input'!D6) -> 100000 | E6: =IF('Start Here'!$B$8="Paste Import",'Paste Import'!E6,'Manual Input'!E6) -> 0 | F6: =IF('Start Here'!$B$8="Paste Import",'Paste Import'!F6,'Manual Input'!F6) -> 80000 | G6: =IF('Start Here'!$B$8="Paste Import",'Paste Import'!G6,'Manual Input'!G6) -> 0 | H6: =IF(B6="","",D6-E6) -> 100000 | I6: =IF(B6="","",F6-G6) -> 80000 | J6: =IF(B6="","",H6-I6) -> 20000 | K6: =IF(B6="","",IF(I6=0,IF(H6=0,"","New"),J6/ABS(I6))) -> 0.25 | L6: =IF('Start Here'!$B$8="Paste Import",'Paste Import'!H6,'Manual Input'!H6) -> Cash | M6: =IF('Start Here'!$B$8="Paste Import",'Paste Import'!I6,'Manual Input'!I6) -> 0 | N6: =IF(B6="","",H6+M6) -> 100000 | O6: =IF(B6="","",IF(OR(C6="",L6=""),"Unmapped","OK")) -> OK | P6: =IF(B6="","",IF(OR(AND(OR(C6="Asset",C6="Expense"),H6<0),AND(OR(C6="Liability",C6="Equity",C6="Revenue"),H6>0)),"Unusual","OK")) -> OK | Q6: =IF(B6="","",IF(AND(ABS(J6)>='Start Here'!$B$10,IFERROR(ABS(K6)>='Start Here'!$B$11,TRUE)),"Review","OK")) -> Review | R6: =IF(B6="","",IF(OR(O6<>"OK",P6<>"OK",Q6<>"OK"),"Review","Complete")) -> Review | S6: =IF('Start Here'!$B$8="Paste Import",'Paste Import'!J6,'Manual Input'!J6) -> Material cash movement
A7: =IF('Start Here'!$B$8="Paste Import",'Paste Import'!A7,'Manual Input'!A7) -> 1100 | B7: =IF('Start Here'!$B$8="Paste Import",'Paste Import'!B7,'Manual Input'!B7) -> Accounts Receivable | C7: =IF('Start Here'!$B$8="Paste Import",'Paste Import'!C7,'Manual Input'!C7) -> Asset | D7: =IF('Start Here'!$B$8="Paste Import",'Paste Import'!D7,'Manual Input'!D7) -> 50000 | E7: =IF('Start Here'!$B$8="Paste Import",'Paste Import'!E7,'Manual Input'!E7) -> 0 | F7: =IF('Start Here'!$B$8="Paste Import",'Paste Import'!F7,'Manual Input'!F7) -> 50000 | G7: =IF('Start Here'!$B$8="Paste Import",'Paste Import'!G7,'Manual Input'!G7) -> 0 | H7: =IF(B7="","",D7-E7) -> 50000 | I7: =IF(B7="","",F7-G7) -> 50000 | J7: =IF(B7="","",H7-I7) -> 0 | K7: =IF(B7="","",IF(I7=0,IF(H7=0,"","New"),J7/ABS(I7))) -> 0 | L7: =IF('Start Here'!$B$8="Paste Import",'Paste Import'!H7,'Manual Input'!H7) -> Receivables | M7: =IF('Start Here'!$B$8="Paste Import",'Paste Import'!I7,'Manual Input'!I7) -> 2000 | N7: =IF(B7="","",H7+M7) -> 52000 | O7: =IF(B7="","",IF(OR(C7="",L7=""),"Unmapped","OK")) -> OK | P7: =IF(B7="","",IF(OR(AND(OR(C7="Asset",C7="Expense"),H7<0),AND(OR(C7="Liability",C7="Equity",C7="Revenue"),H7>0)),"Unusual","OK")) -> OK | Q7: =IF(B7="","",IF(AND(ABS(J7)>='Start Here'!$B$10,IFERROR(ABS(K7)>='Start Here'!$B$11,TRUE)),"Review","OK")) -> OK | R7: =IF(B7="","",IF(OR(O7<>"OK",P7<>"OK",Q7<>"OK"),"Review","Complete")) -> Complete | S7: =IF('Start Here'!$B$8="Paste Import",'Paste Import'!J7,'Manual Input'!J7) -> Proposed debit adjustment
A8: =IF('Start Here'!$B$8="Paste Import",'Paste Import'!A8,'Manual Input'!A8) -> 1200 | B8: =IF('Start Here'!$B$8="Paste Import",'Paste Import'!B8,'Manual Input'!B8) -> Inventory | C8: =IF('Start Here'!$B$8="Paste Import",'Paste Import'!C8,'Manual Input'!C8) -> Asset | D8: =IF('Start Here'!$B$8="Paste Import",'Paste Import'!D8,'Manual Input'!D8) -> 30000 | E8: =IF('Start Here'!$B$8="Paste Import",'Paste Import'!E8,'Manual Input'!E8) -> 0 | F8: =IF('Start Here'!$B$8="Paste Import",'Paste Import'!F8,'Manual Input'!F8) -> 20000 | G8: =IF('Start Here'!$B$8="Paste Import",'Paste Import'!G8,'Manual Input'!G8) -> 0 | H8: =IF(B8="","",D8-E8) -> 30000 | I8: =IF(B8="","",F8-G8) -> 20000 | J8: =IF(B8="","",H8-I8) -> 10000 | K8: =IF(B8="","",IF(I8=0,IF(H8=0,"","New"),J8/ABS(I8))) -> 0.5 | L8: =IF('Start Here'!$B$8="Paste Import",'Paste Import'!H8,'Manual Input'!H8) -> Inventory | M8: =IF('Start Here'!$B$8="Paste Import",'Paste Import'!I8,'Manual Input'!I8) -> 0 | N8: =IF(B8="","",H8+M8) -> 30000 | O8: =IF(B8="","",IF(OR(C8="",L8=""),"Unmapped","OK")) -> OK | P8: =IF(B8="","",IF(OR(AND(OR(C8="Asset",C8="Expense"),H8<0),AND(OR(C8="Liability",C8="Equity",C8="Revenue"),H8>0)),"Unusual","OK")) -> OK | Q8: =IF(B8="","",IF(AND(ABS(J8)>='Start Here'!$B$10,IFERROR(ABS(K8)>='Start Here'!$B$11,TRUE)),"Review","OK")) -> Review | R8: =IF(B8="","",IF(OR(O8<>"OK",P8<>"OK",Q8<>"OK"),"Review","Complete")) -> Review | S8: =IF('Start Here'!$B$8="Paste Import",'Paste Import'!J8,'Manual Input'!J8) -> Growth requires review
A9: =IF('Start Here'!$B$8="Paste Import",'Paste Import'!A9,'Manual Input'!A9) -> 1300 | B9: =IF('Start Here'!$B$8="Paste Import",'Paste Import'!B9,'Manual Input'!B9) -> Prepaid Expenses | C9: =IF('Start Here'!$B$8="Paste Import",'Paste Import'!C9,'Manual Input'!C9) -> Asset | D9: =IF('Start Here'!$B$8="Paste Import",'Paste Import'!D9,'Manual Input'!D9) -> 5000 | E9: =IF('Start Here'!$B$8="Paste Import",'Paste Import'!E9,'Manual Input'!E9) -> 0 | F9: =IF('Start Here'!$B$8="Paste Import",'Paste Import'!F9,'Manual Input'!F9) -> 5000 | G9: =IF('Start Here'!$B$8="Paste Import",'Paste Import'!G9,'Manual Input'!G9) -> 0 | H9: =IF(B9="","",D9-E9) -> 5000 | I9: =IF(B9="","",F9-G9) -> 5000 | J9: =IF(B9="","",H9-I9) -> 0 | K9: =IF(B9="","",IF(I9=0,IF(H9=0,"","New"),J9/ABS(I9))) -> 0 | L9: =IF('Start Here'!$B$8="Paste Import",'Paste Import'!H9,'Manual Input'!H9) -> Other | M9: =IF('Start Here'!$B$8="Paste Import",'Paste Import'!I9,'Manual Input'!I9) -> 0 | N9: =IF(B9="","",H9+M9) -> 5000 | O9: =IF(B9="","",IF(OR(C9="",L9=""),"Unmapped","OK")) -> OK | P9: =IF(B9="","",IF(OR(AND(OR(C9="Asset",C9="Expense"),H9<0),AND(OR(C9="Liability",C9="Equity",C9="Revenue"),H9>0)),"Unusual","OK")) -> OK | Q9: =IF(B9="","",IF(AND(ABS(J9)>='Start Here'!$B$10,IFERROR(ABS(K9)>='Start Here'!$B$11,TRUE)),"Review","OK")) -> OK | R9: =IF(B9="","",IF(OR(O9<>"OK",P9<>"OK",Q9<>"OK"),"Review","Complete")) -> Complete | S9: =IF('Start Here'!$B$8="Paste Import",'Paste Import'!J9,'Manual Input'!J9)
A10: =IF('Start Here'!$B$8="Paste Import",'Paste Import'!A10,'Manual Input'!A10) -> 1500 | B10: =IF('Start Here'!$B$8="Paste Import",'Paste Import'!B10,'Manual Input'!B10) -> Property and Equipment | C10: =IF('Start Here'!$B$8="Paste Import",'Paste Import'!C10,'Manual Input'!C10) -> Asset | D10: =IF('Start Here'!$B$8="Paste Import",'Paste Import'!D10,'Manual Input'!D10) -> 80000 | E10: =IF('Start Here'!$B$8="Paste Import",'Paste Import'!E10,'Manual Input'!E10) -> 0 | F10: =IF('Start Here'!$B$8="Paste Import",'Paste Import'!F10,'Manual Input'!F10) -> 75000 | G10: =IF('Start Here'!$B$8="Paste Import",'Paste Import'!G10,'Manual Input'!G10) -> 0 | H10: =IF(B10="","",D10-E10) -> 80000 | I10: =IF(B10="","",F10-G10) -> 75000 | J10: =IF(B10="","",H10-I10) -> 5000 | K10: =IF(B10="","",IF(I10=0,IF(H10=0,"","New"),J10/ABS(I10))) -> 0.066666667 | L10: =IF('Start Here'!$B$8="Paste Import",'Paste Import'!H10,'Manual Input'!H10) -> Fixed Assets | M10: =IF('Start Here'!$B$8="Paste Import",'Paste Import'!I10,'Manual Input'!I10) -> 0 | N10: =IF(B10="","",H10+M10) -> 80000 | O10: =IF(B10="","",IF(OR(C10="",L10=""),"Unmapped","OK")) -> OK | P10: =IF(B10="","",IF(OR(AND(OR(C10="Asset",C10="Expense"),H10<0),AND(OR(C10="Liability",C10="Equity",C10="Revenue"),H10>0)),"Unusual","OK")) -> OK | Q10: =IF(B10="","",IF(AND(ABS(J10)>='Start Here'!$B$10,IFERROR(ABS(K10)>='Start Here'!$B$11,TRUE)),"Review","OK")) -> OK | R10: =IF(B10="","",IF(OR(O10<>"OK",P10<>"OK",Q10<>"OK"),"Review","Complete")) -> Complete | S10: =IF('Start Here'!$B$8="Paste Import",'Paste Import'!J10,'Manual Input'!J10)
A11: =IF('Start Here'!$B$8="Paste Import",'Paste Import'!A11,'Manual Input'!A11) -> 1590 | B11: =IF('Start Here'!$B$8="Paste Import",'Paste Import'!B11,'Manual Input'!B11) -> Accumulated Depreciation | C11: =IF('Start Here'!$B$8="Paste Import",'Paste Import'!C11,'Manual Input'!C11) -> Asset | D11: =IF('Start Here'!$B$8="Paste Import",'Paste Import'!D11,'Manual Input'!D11) -> 0 | E11: =IF('Start Here'!$B$8="Paste Import",'Paste Import'!E11,'Manual Input'!E11) -> 25000 | F11: =IF('Start Here'!$B$8="Paste Import",'Paste Import'!F11,'Manual Input'!F11) -> 0 | G11: =IF('Start Here'!$B$8="Paste Import",'Paste Import'!G11,'Manual Input'!G11) -> 20000 | H11: =IF(B11="","",D11-E11) -> -25000 | I11: =IF(B11="","",F11-G11) -> -20000 | J11: =IF(B11="","",H11-I11) -> -5000 | K11: =IF(B11="","",IF(I11=0,IF(H11=0,"","New"),J11/ABS(I11))) -> -0.25 | L11: =IF('Start Here'!$B$8="Paste Import",'Paste Import'!H11,'Manual Input'!H11) -> Fixed Assets | M11: =IF('Start Here'!$B$8="Paste Import",'Paste Import'!I11,'Manual Input'!I11) -> 0 | N11: =IF(B11="","",H11+M11) -> -25000 | O11: =IF(B11="","",IF(OR(C11="",L11=""),"Unmapped","OK")) -> OK | P11: =IF(B11="","",IF(OR(AND(OR(C11="Asset",C11="Expense"),H11<0),AND(OR(C11="Liability",C11="Equity",C11="Revenue"),H11>0)),"Unusual","OK")) -> Unusual | Q11: =IF(B11="","",IF(AND(ABS(J11)>='Start Here'!$B$10,IFERROR(ABS(K11)>='Start Here'!$B$11,TRUE)),"Review","OK")) -> Review | R11: =IF(B11="","",IF(OR(O11<>"OK",P11<>"OK",Q11<>"OK"),"Review","Complete")) -> Review | S11: =IF('Start Here'!$B$8="Paste Import",'Paste Import'!J11,'Manual Input'!J11) -> Credit balance flagged by sign rule
A12: =IF('Start Here'!$B$8="Paste Import",'Paste Import'!A12,'Manual Input'!A12) -> 2000 | B12: =IF('Start Here'!$B$8="Paste Import",'Paste Import'!B12,'Manual Input'!B12) -> Accounts Payable | C12: =IF('Start Here'!$B$8="Paste Import",'Paste Import'!C12,'Manual Input'!C12) -> Liability | D12: =IF('Start Here'!$B$8="Paste Import",'Paste Import'!D12,'Manual Input'!D12) -> 0 | E12: =IF('Start Here'!$B$8="Paste Import",'Paste Import'!E12,'Manual Input'!E12) -> 40000 | F12: =IF('Start Here'!$B$8="Paste Import",'Paste Import'!F12,'Manual Input'!F12) -> 0 | G12: =IF('Start Here'!$B$8="Paste Import",'Paste Import'!G12,'Manual Input'!G12) -> 35000 | H12: =IF(B12="","",D12-E12) -> -40000 | I12: =IF(B12="","",F12-G12) -> -35000 | J12: =IF(B12="","",H12-I12) -> -5000 | K12: =IF(B12="","",IF(I12=0,IF(H12=0,"","New"),J12/ABS(I12))) -> -0.14285714 | L12: =IF('Start Here'!$B$8="Paste Import",'Paste Import'!H12,'Manual Input'!H12) -> Payables | M12: =IF('Start Here'!$B$8="Paste Import",'Paste Import'!I12,'Manual Input'!I12) -> 0 | N12: =IF(B12="","",H12+M12) -> -40000 | O12: =IF(B12="","",IF(OR(C12="",L12=""),"Unmapped","OK")) -> OK | P12: =IF(B12="","",IF(OR(AND(OR(C12="Asset",C12="Expense"),H12<0),AND(OR(C12="Liability",C12="Equity",C12="Revenue"),H12>0)),"Unusual","OK")) -> OK | Q12: =IF(B12="","",IF(AND(ABS(J12)>='Start Here'!$B$10,IFERROR(ABS(K12)>='Start Here'!$B$11,TRUE)),"Review","OK")) -> Review | R12: =IF(B12="","",IF(OR(O12<>"OK",P12<>"OK",Q12<>"OK"),"Review","Complete")) -> Review | S12: =IF('Start Here'!$B$8="Paste Import",'Paste Import'!J12,'Manual Input'!J12)
A13: =IF('Start Here'!$B$8="Paste Import",'Paste Import'!A13,'Manual Input'!A13) -> 2100 | B13: =IF('Start Here'!$B$8="Paste Import",'Paste Import'!B13,'Manual Input'!B13) -> Accrued Expenses | C13: =IF('Start Here'!$B$8="Paste Import",'Paste Import'!C13,'Manual Input'!C13) -> Liability | D13: =IF('Start Here'!$B$8="Paste Import",'Paste Import'!D13,'Manual Input'!D13) -> 0 | E13: =IF('Start Here'!$B$8="Paste Import",'Paste Import'!E13,'Manual Input'!E13) -> 15000 | F13: =IF('Start Here'!$B$8="Paste Import",'Paste Import'!F13,'Manual Input'!F13) -> 0 | G13: =IF('Start Here'!$B$8="Paste Import",'Paste Import'!G13,'Manual Input'!G13) -> 10000 | H13: =IF(B13="","",D13-E13) -> -15000 | I13: =IF(B13="","",F13-G13) -> -10000 | J13: =IF(B13="","",H13-I13) -> -5000 | K13: =IF(B13="","",IF(I13=0,IF(H13=0,"","New"),J13/ABS(I13))) -> -0.5 | L13: =IF('Start Here'!$B$8="Paste Import",'Paste Import'!H13,'Manual Input'!H13) -> Payables | M13: =IF('Start Here'!$B$8="Paste Import",'Paste Import'!I13,'Manual Input'!I13) -> 0 | N13: =IF(B13="","",H13+M13) -> -15000 | O13: =IF(B13="","",IF(OR(C13="",L13=""),"Unmapped","OK")) -> OK | P13: =IF(B13="","",IF(OR(AND(OR(C13="Asset",C13="Expense"),H13<0),AND(OR(C13="Liability",C13="Equity",C13="Revenue"),H13>0)),"Unusual","OK")) -> OK | Q13: =IF(B13="","",IF(AND(ABS(J13)>='Start Here'!$B$10,IFERROR(ABS(K13)>='Start Here'!$B$11,TRUE)),"Review","OK")) -> Review | R13: =IF(B13="","",IF(OR(O13<>"OK",P13<>"OK",Q13<>"OK"),"Review","Complete")) -> Review | S13: =IF('Start Here'!$B$8="Paste Import",'Paste Import'!J13,'Manual Input'!J13)
A14: =IF('Start Here'!$B$8="Paste Import",'Paste Import'!A14,'Manual Input'!A14) -> 2500 | B14: =IF('Start Here'!$B$8="Paste Import",'Paste Import'!B14,'Manual Input'!B14) -> Term Debt | C14: =IF('Start Here'!$B$8="Paste Import",'Paste Import'!C14,'Manual Input'!C14) -> Liability | D14: =IF('Start Here'!$B$8="Paste Import",'Paste Import'!D14,'Manual Input'!D14) -> 0 | E14: =IF('Start Here'!$B$8="Paste Import",'Paste Import'!E14,'Manual Input'!E14) -> 60000 | F14: =IF('Start Here'!$B$8="Paste Import",'Paste Import'!F14,'Manual Input'!F14) -> 0 | G14: =IF('Start Here'!$B$8="Paste Import",'Paste Import'!G14,'Manual Input'!G14) -> 55000 | H14: =IF(B14="","",D14-E14) -> -60000 | I14: =IF(B14="","",F14-G14) -> -55000 | J14: =IF(B14="","",H14-I14) -> -5000 | K14: =IF(B14="","",IF(I14=0,IF(H14=0,"","New"),J14/ABS(I14))) -> -0.090909091 | L14: =IF('Start Here'!$B$8="Paste Import",'Paste Import'!H14,'Manual Input'!H14) -> Debt | M14: =IF('Start Here'!$B$8="Paste Import",'Paste Import'!I14,'Manual Input'!I14) -> 0 | N14: =IF(B14="","",H14+M14) -> -60000 | O14: =IF(B14="","",IF(OR(C14="",L14=""),"Unmapped","OK")) -> OK | P14: =IF(B14="","",IF(OR(AND(OR(C14="Asset",C14="Expense"),H14<0),AND(OR(C14="Liability",C14="Equity",C14="Revenue"),H14>0)),"Unusual","OK")) -> OK | Q14: =IF(B14="","",IF(AND(ABS(J14)>='Start Here'!$B$10,IFERROR(ABS(K14)>='Start Here'!$B$11,TRUE)),"Review","OK")) -> OK | R14: =IF(B14="","",IF(OR(O14<>"OK",P14<>"OK",Q14<>"OK"),"Review","Complete")) -> Complete | S14: =IF('Start Here'!$B$8="Paste Import",'Paste Import'!J14,'Manual Input'!J14)
A15: =IF('Start Here'!$B$8="Paste Import",'Paste Import'!A15,'Manual Input'!A15) -> 3000 | B15: =IF('Start Here'!$B$8="Paste Import",'Paste Import'!B15,'Manual Input'!B15) -> Members' Equity | C15: =IF('Start Here'!$B$8="Paste Import",'Paste Import'!C15,'Manual Input'!C15) -> Equity | D15: =IF('Start Here'!$B$8="Paste Import",'Paste Import'!D15,'Manual Input'!D15) -> 0 | E15: =IF('Start Here'!$B$8="Paste Import",'Paste Import'!E15,'Manual Input'!E15) -> 110000 | F15: =IF('Start Here'!$B$8="Paste Import",'Paste Import'!F15,'Manual Input'!F15) -> 0 | G15: =IF('Start Here'!$B$8="Paste Import",'Paste Import'!G15,'Manual Input'!G15) -> 95000 | H15: =IF(B15="","",D15-E15) -> -110000 | I15: =IF(B15="","",F15-G15) -> -95000 | J15: =IF(B15="","",H15-I15) -> -15000 | K15: =IF(B15="","",IF(I15=0,IF(H15=0,"","New"),J15/ABS(I15))) -> -0.15789474 | L15: =IF('Start Here'!$B$8="Paste Import",'Paste Import'!H15,'Manual Input'!H15) -> Equity | M15: =IF('Start Here'!$B$8="Paste Import",'Paste Import'!I15,'Manual Input'!I15) -> 0 | N15: =IF(B15="","",H15+M15) -> -110000 | O15: =IF(B15="","",IF(OR(C15="",L15=""),"Unmapped","OK")) -> OK | P15: =IF(B15="","",IF(OR(AND(OR(C15="Asset",C15="Expense"),H15<0),AND(OR(C15="Liability",C15="Equity",C15="Revenue"),H15>0)),"Unusual","OK")) -> OK | Q15: =IF(B15="","",IF(AND(ABS(J15)>='Start Here'!$B$10,IFERROR(ABS(K15)>='Start Here'!$B$11,TRUE)),"Review","OK")) -> Review | R15: =IF(B15="","",IF(OR(O15<>"OK",P15<>"OK",Q15<>"OK"),"Review","Complete")) -> Review | S15: =IF('Start Here'!$B$8="Paste Import",'Paste Import'!J15,'Manual Input'!J15)
A16: =IF('Start Here'!$B$8="Paste Import",'Paste Import'!A16,'Manual Input'!A16) -> 4000 | B16: =IF('Start Here'!$B$8="Paste Import",'Paste Import'!B16,'Manual Input'!B16) -> Product Revenue | C16: =IF('Start Here'!$B$8="Paste Import",'Paste Import'!C16,'Manual Input'!C16) -> Revenue | D16: =IF('Start Here'!$B$8="Paste Import",'Paste Import'!D16,'Manual Input'!D16) -> 0 | E16: =IF('Start Here'!$B$8="Paste Import",'Paste Import'!E16,'Manual Input'!E16) -> 200000 | F16: =IF('Start Here'!$B$8="Paste Import",'Paste Import'!F16,'Manual Input'!F16) -> 0 | G16: =IF('Start Here'!$B$8="Paste Import",'Paste Import'!G16,'Manual Input'!G16) -> 180000 | H16: =IF(B16="","",D16-E16) -> -200000 | I16: =IF(B16="","",F16-G16) -> -180000 | J16: =IF(B16="","",H16-I16) -> -20000 | K16: =IF(B16="","",IF(I16=0,IF(H16=0,"","New"),J16/ABS(I16))) -> -0.11111111 | L16: =IF('Start Here'!$B$8="Paste Import",'Paste Import'!H16,'Manual Input'!H16) -> Revenue | M16: =IF('Start Here'!$B$8="Paste Import",'Paste Import'!I16,'Manual Input'!I16) -> -2000 | N16: =IF(B16="","",H16+M16) -> -202000 | O16: =IF(B16="","",IF(OR(C16="",L16=""),"Unmapped","OK")) -> OK | P16: =IF(B16="","",IF(OR(AND(OR(C16="Asset",C16="Expense"),H16<0),AND(OR(C16="Liability",C16="Equity",C16="Revenue"),H16>0)),"Unusual","OK")) -> OK | Q16: =IF(B16="","",IF(AND(ABS(J16)>='Start Here'!$B$10,IFERROR(ABS(K16)>='Start Here'!$B$11,TRUE)),"Review","OK")) -> Review | R16: =IF(B16="","",IF(OR(O16<>"OK",P16<>"OK",Q16<>"OK"),"Review","Complete")) -> Review | S16: =IF('Start Here'!$B$8="Paste Import",'Paste Import'!J16,'Manual Input'!J16) -> Proposed credit adjustment
A17: =IF('Start Here'!$B$8="Paste Import",'Paste Import'!A17,'Manual Input'!A17) -> 5000 | B17: =IF('Start Here'!$B$8="Paste Import",'Paste Import'!B17,'Manual Input'!B17) -> Cost of Goods Sold | C17: =IF('Start Here'!$B$8="Paste Import",'Paste Import'!C17,'Manual Input'!C17) -> Expense | D17: =IF('Start Here'!$B$8="Paste Import",'Paste Import'!D17,'Manual Input'!D17) -> 100000 | E17: =IF('Start Here'!$B$8="Paste Import",'Paste Import'!E17,'Manual Input'!E17) -> 0 | F17: =IF('Start Here'!$B$8="Paste Import",'Paste Import'!F17,'Manual Input'!F17) -> 90000 | G17: =IF('Start Here'!$B$8="Paste Import",'Paste Import'!G17,'Manual Input'!G17) -> 0 | H17: =IF(B17="","",D17-E17) -> 100000 | I17: =IF(B17="","",F17-G17) -> 90000 | J17: =IF(B17="","",H17-I17) -> 10000 | K17: =IF(B17="","",IF(I17=0,IF(H17=0,"","New"),J17/ABS(I17))) -> 0.11111111 | L17: =IF('Start Here'!$B$8="Paste Import",'Paste Import'!H17,'Manual Input'!H17) -> Operating Expenses | M17: =IF('Start Here'!$B$8="Paste Import",'Paste Import'!I17,'Manual Input'!I17) -> 0 | N17: =IF(B17="","",H17+M17) -> 100000 | O17: =IF(B17="","",IF(OR(C17="",L17=""),"Unmapped","OK")) -> OK | P17: =IF(B17="","",IF(OR(AND(OR(C17="Asset",C17="Expense"),H17<0),AND(OR(C17="Liability",C17="Equity",C17="Revenue"),H17>0)),"Unusual","OK")) -> OK | Q17: =IF(B17="","",IF(AND(ABS(J17)>='Start Here'!$B$10,IFERROR(ABS(K17)>='Start Here'!$B$11,TRUE)),"Review","OK")) -> Review | R17: =IF(B17="","",IF(OR(O17<>"OK",P17<>"OK",Q17<>"OK"),"Review","Complete")) -> Review | S17: =IF('Start Here'!$B$8="Paste Import",'Paste Import'!J17,'Manual Input'!J17)
... A105: =IF('Start Here'!$B$8="Paste Import",'Paste Import'!A105,'Manual Input'!A105) | B105: =IF('Start Here'!$B$8="Paste Import",'Paste Import'!B105,'Manual Input'!B105) | C105: =IF('Start Here'!$B$8="Paste Import",'Paste Import'!C105,'Manual Input'!C105) | D105: =IF('Start Here'!$B$8="Paste Import",'Paste Import'!D105,'Manual Input'!D105) | E105: =IF('Start Here'!$B$8="Paste Import",'Paste Import'!E105,'Manual Input'!E105) | F105: =IF('Start Here'!$B$8="Paste Import",'Paste Import'!F105,'Manual Input'!F105) | G105: =IF('Start Here'!$B$8="Paste Import",'Paste Import'!G105,'Manual Input'!G105) | H105: =IF(B105="","",D105-E105) | I105: =IF(B105="","",F105-G105) | J105: =IF(B105="","",H105-I105) | K105: =IF(B105="","",IF(I105=0,IF(H105=0,"","New"),J105/ABS(I105))) | L105: =IF('Start Here'!$B$8="Paste Import",'Paste Import'!H105,'Manual Input'!H105) | M105: =IF('Start Here'!$B$8="Paste Import",'Paste Import'!I105,'Manual Input'!I105) | N105: =IF(B105="","",H105+M105) | O105: =IF(B105="","",IF(OR(C105="",L105=""),"Unmapped","OK")) | P105: =IF(B105="","",IF(OR(AND(OR(C105="Asset",C105="Expense"),H105<0),AND(OR(C105="Liability",C105="Equity",C105="Revenue"),H105>0)),"Unusual","OK")) | Q105: =IF(B105="","",IF(AND(ABS(J105)>='Start Here'!$B$10,IFERROR(ABS(K105)>='Start Here'!$B$11,TRUE)),"Review","OK")) | R105: =IF(B105="","",IF(OR(O105<>"OK",P105<>"OK",Q105<>"OK"),"Review","Complete")) | S105: =IF('Start Here'!$B$8="Paste Import",'Paste Import'!J105,'Manual Input'!J105)

Sheet Summary
A1: Trial Balance Review — Summary
A3: Printable balance, adjustment, mapping, sign, and materiality controls
A5: Client | B5: ='Start Here'!B4 -> Northstar Components LLC | C5: Period End | D5: ='Start Here'!B5 -> 46203 | E5: Prepared By | F5: ='Start Here'!B6 -> Taylor Morgan | G5: Status | H5: =IF(AND(ABS(D12)<0.01,F15=0),"Complete","Review") -> Review
A8: Current Debits | C8: Current Credits | E8: Current Difference
B9: =SUM('Review'!$D$6:$D$105) -> 450000 | D9: =SUM('Review'!$E$6:$E$105) -> 450000 | F9: =B9-D9 -> 0
A11: Proposed Adjustments | C11: Adjusted Difference | E11: Material Movement Count
B12: =SUM('Review'!$M$6:$M$105) -> 0 | D12: =F9+B12 -> 0 | F12: =COUNTIF('Review'!$Q$6:$Q$105,"Review") -> 9
A14: Unusual Sign Count | C14: Unmapped Count | E14: Open Review Count
B15: =COUNTIF('Review'!$P$6:$P$105,"Unusual") -> 1 | D15: =COUNTIF('Review'!$O$6:$O$105,"Unmapped") -> 1 | F15: =COUNTIF('Review'!$R$6:$R$105,"Review") -> 9
A18: Reviewer Notes
A19: Resolve mapping, unusual-sign, and material-movement review items before sign-off. Proposed adjustments use positive debit and negative credit signs.

Sheet Lists
A1: Account Type | B1: Review Category | C1: Status | D1: Input Mode
A2: Asset | B2: Cash | C2: Review | D2: Paste Import
A3: Liability | B3: Receivables | C3: Complete | D3: Manual Input
A4: Equity | B4: Inventory | C4: OK
A5: Revenue | B5: Fixed Assets | C5: Unmapped
A6: Expense | B6: Payables | C6: Unusual
A7: Other | B7: Debt
B8: Equity
B9: Revenue
B10: Operating Expenses
B11: Other
